Workbook

Sheet Overview
A1: Allegheny County Sheriff Sale — Monday, November 2, 2026
A2: Source: November-Sale-List-Updated-10-22.pdf (printed 10/22/2026 2:51:38PM). Updated Wed Oct 28, 2026 4:31 AM.
A4: OK to Sell | B4: 105 | C4: Sum of opening bids: $2,248,676
A5: Almost Ready (needs only 3129.3 / verify) | B5: 17 | C5: Sum of opening bids: $492,954
A6: Residential cases still active but not ready | B6: 156
A7: All cases on the Sheriff's list | B7: 430
A9: Changes since the last update (2026-10-26 04:31)
A10: No changes to OK to Sell or Almost Ready.
A12: Update log
A13: Updated | B13: OK to Sell | C13: Source file | D13: Almost Ready
A14: 2026-10-25 22:15 | B14: 105 | C14: November-Sale-List-Updated-10-22.pdf (printed 10/22/2026 2:51:38PM) | D14: 17
A15: 2026-10-26 04:31 | B15: 105 | C15: November-Sale-List-Updated-10-22.pdf (printed 10/22/2026 2:51:38PM) | D15: 17
A16: 2026-10-28 04:31 | B16: 105 | C16: November-Sale-List-Updated-10-22.pdf (printed 10/22/2026 2:51:38PM) | D16: 17
A18: How to use: type only in the yellow YOUR ENTRY columns on OK to Sell / Almost Ready (assessed value fills in the transfer-tax estimate). Every update keeps what you typed, matched by Sale ID. The Sheriff finalizes the list the morning of the sale — check the morning-of list before bidding. Not legal advice; see Glossary.

Sheet OK to Sell
A1: OK to Sell — Mon Nov 2
A2: Active residential cases with the Sheriff's OK box checked and nothing outstanding except possibly Rule 3129.3. Status can still change before the sale.
A4: Sale ID | B4: Case # | C4: Property address | D4: City | E4: ZIP | F4: Municipality | G4: Parcel ID(s) | H4: County parcel ID (portal format) | I4: Property type | J4: Sale category | K4: Owner type | L4: Defendant / owner | M4: Plaintiff | N4: Plaintiff attorney | O4: Cost & Tax bid | P4: Free & clear min bid | Q4: Opening bid to watch | R4: Reassessed damages (judgment) | S4: Boxes Svs · 3129.2 · 3129.3 · OK | T4: Readiness note | U4: Flags / title & bidding risks | V4: Sheriff comments (verbatim) | W4: Transfer tax municipality | X4: Transfer tax rate (total) | Y4: YOUR ENTRY: Assessed value | Z4: Est. transfer tax on sheriff deed | AA4: YOUR ENTRY: Max bid | AB4: YOUR ENTRY: My notes | AC4: YOUR ENTRY: Sold for | AD4: YOUR ENTRY: Bidder # | AE4: First listed here
A5: 97NOV26 | B5: GD-21-000668 | C5: 215 Union Avenue | D5: Pittsburgh | E5: 15202 | F5: Avalon | G5: 215-P-333 | H5: 0215-P-00333-0000-00 | I5: Residential / unspecified | J5: Tax lien (Sci Fa sur tax lien) | K5: Individual | L5: Seth, Robert A. | M5: Borough of Avalon | N5: GOEHRING RUTTER & BOEHM | O5: 21673.25 | Q5: 21673.25 | S5: ✔ ✔ – ✔ | T5: Sheriff OK box checked | V5: OK TO SELL 11/2/26 | W5: Avalon Boro | X5: =IFERROR(VLOOKUP(W5,'Transfer Tax'!$A$14:$H$400,8,FALSE),"") | Z5: =IF(OR(Y5="",X5=""),"",Y5*'Transfer Tax'!$B$6*X5) | AE5: 2026-10-25
A6: 101NOV26 | B6: GD-25-006792 | C6: 925 Jackman Ave | D6: Pittsburgh | E6: 15202 | F6: Avalon | G6: 160-J-93 | H6: 0160-J-00093-0000-00 | I6: Residential / unspecified | J6: Tax lien (Sci Fa sur tax lien) | K6: Individual | L6: Hellerman, Allen B. | M6: Borough of Avalon | N6: GOEHRING RUTTER & BOEHM | O6: 136212.1 | Q6: 136212.1 | S6: ✔ ✔ – ✔ | T6: Sheriff OK box checked | V6: OK TO SELL 11/2/26 | W6: Avalon Boro | X6: =IFERROR(VLOOKUP(W6,'Transfer Tax'!$A$14:$H$400,8,FALSE),"") | Z6: =IF(OR(Y6="",X6=""),"",Y6*'Transfer Tax'!$B$6*X6) | AE6: 2026-10-25
A7: 9SEP26 | B7: MG-26-000258 | C7: 929 Sedalia Avenue | D7: Pittsburgh | E7: 15202 | F7: Avalon | G7: 215-J-249 | H7: 0215-J-00249-0000-00 | I7: Residential / unspecified | J7: Mortgage foreclosure | K7: Individual | L7: Henry, Autumn M. | M7: Lakeview Loan Servicing LLC | N7: KML LAW GROUP | O7: 2063.72 | Q7: 2063.72 | R7: 94376.8 | S7: ✔ ✔ ✔ ✔ | T7: Sheriff OK box checked | V7: OK TO SELL 11-2-26 O/C TO REASSESS DAMAGES TO $94,376.80 | W7: Avalon Boro | X7: =IFERROR(VLOOKUP(W7,'Transfer Tax'!$A$14:$H$400,8,FALSE),"") | Z7: =IF(OR(Y7="",X7=""),"",Y7*'Transfer Tax'!$B$6*X7) | AE7: 2026-10-25
A8: 2NOV26 | B8: GD-23-010808 | C8: 2670 Broad Street | D8: Bethel Park | E8: 15102 | F8: Bethel Park | G8: 476-C-23 | H8: 0476-C-00023-0000-00 | I8: Residential / unspecified | J8: Tax lien (Sci Fa sur tax lien) | K8: Individual | L8: McGuire, Patrick T | M8: Bethel Park School District | N8: WEISS BURKARDT KRAMER LLC | O8: 40854.87 | Q8: 40854.87 | S8: ✔ ✔ – ✔ | T8: Sheriff OK box checked | V8: OK TO SELL 11/2/26 | W8: Bethel Park Municipality | X8: =IFERROR(VLOOKUP(W8,'Transfer Tax'!$A$14:$H$400,8,FALSE),"") | Z8: =IF(OR(Y8="",X8=""),"",Y8*'Transfer Tax'!$B$6*X8) | AE8: 2026-10-25
A9: 8NOV26 | B9: MG-22-000715 | C9: 442 Limestone Drive | D9: Bethel Park | E9: 15102 | F9: Bethel Park | G9: 774-E-20 | H9: 0774-E-00020-0000-00 | I9: Residential / unspecified | J9: Mortgage foreclosure | K9: Individual | L9: Lucido, Erin E | M9: U.S. Bank Trust National Association | N9: HLADIK ONORATO AND FEDERMAN LLP | O9: 14091.23 | Q9: 14091.23 | R9: 324967.67 | S9: ✔ ✔ – ✔ | T9: Sheriff OK box checked | V9: OK TO SELL 11/2/26 RCVD O/C TO REASSESS DAMAGES $324,967.67 | W9: Bethel Park Municipality | X9: =IFERROR(VLOOKUP(W9,'Transfer Tax'!$A$14:$H$400,8,FALSE),"") | Z9: =IF(OR(Y9="",X9=""),"",Y9*'Transfer Tax'!$B$6*X9) | AE9: 2026-10-25
A10: 50OCT26 | B10: GD-25-003997 | C10: 5919 Dorlyn Drive | D10: Bethel Park | E10: 15102 | F10: Bethel Park | G10: 773-A-132 | H10: 0773-A-00132-0000-00 | I10: Residential / unspecified | J10: Tax lien (Sci Fa sur tax lien) | K10: Individual | L10: Slifer, Richel | M10: County of Allegheny | N10: GOEHRING RUTTER & BOEHM | O10: 38158.07 | Q10: 38158.07 | S10: ✔ ✔ ✔ ✔ | T10: Sheriff OK box checked | V10: OK TO SELL 11-2-26 | W10: Bethel Park Municipality | X10: =IFERROR(VLOOKUP(W10,'Transfer Tax'!$A$14:$H$400,8,FALSE),"") | Z10: =IF(OR(Y10="",X10=""),"",Y10*'Transfer Tax'!$B$6*X10) | AE10: 2026-10-25
A11: 64NOV26 | B11: MG-26-000083 | C11: 213 Comrie Avenue | D11: Braddock | E11: 15104 | F11: Braddock | G11: 236-M-311 | H11: 0236-M-00311-0000-00 | I11: Residential / unspecified | J11: Mortgage foreclosure | K11: Individual | L11: Strozier, Erica R. | M11: Pennsylvania Housing Finance Agency | N11: PURCELL KRUG & HALLER | O11: 2108.6 | Q11: 2108.6 | S11: ✔ ✔ – ✔ | T11: Sheriff OK box checked | V11: OK TO SELL 11/2/26 | W11: Braddock Boro | X11: =IFERROR(VLOOKUP(W11,'Transfer Tax'!$A$14:$H$400,8,FALSE),"") | Z11: =IF(OR(Y11="",X11=""),"",Y11*'Transfer Tax'!$B$6*X11) | AE11: 2026-10-25
A12: 67MAR26 | B12: MG-25-000393 | C12: 125 Olancha Avenue | D12: Pittsburgh | E12: 15227 | F12: Brentwood | G12: 188-F-198 | H12: 0188-F-00198-0000-00 | I12: Residential / unspecified | J12: Mortgage foreclosure | K12: Individual | L12: Lucas, Christina Kathryn | M12: Lakeview Loan Servicing LLC | N12: HLADIK ONORATO AND FEDERMAN LLP | O12: 6387.14 | Q12: 6387.14 | S12: ✔ ✔ ✔ ✔ | T12: Sheriff OK box checked | V12: OK TO SELL 11-2-26 | W12: Brentwood Boro | X12: =IFERROR(VLOOKUP(W12,'Transfer Tax'!$A$14:$H$400,8,FALSE),"") | Z12: =IF(OR(Y12="",X12=""),"",Y12*'Transfer Tax'!$B$6*X12) | AE12: 2026-10-25
A13: 2NOV24 | B13: GD-23-014272 | C13: 61 Bellanca Avenue | D13: Pittsburgh | E13: 15227 | F13: Brentwood | G13: 137-E-315 | H13: 0137-E-00315-0000-00 | I13: Residential / unspecified | J13: Tax lien (Sci Fa sur tax lien) | K13: Individual | L13: Riland, Laura J | M13: Brentwood Borough School District | N13: TUCKER ARENSBURG PC | O13: 66430.88 | P13: 14000 | Q13: 14000 | R13: 38493.85 | S13: ✔ ✔ ✔ ✔ | T13: Sheriff OK box checked | U13: Free & clear court order, min bid $14,000.00 Bankruptcy history: 2 filing(s) | V13: OK TO SELL 11-2-26 F/C O/C FOR A MIN BID OF $14,000.00 CHP 13 BK FILED ON 10-31-24 CN-24-22661-GLT BKD RCVD 3-7-25 CHP 13 BK RCVD ON 4-25-25 CN-25-21038 -GLT BKD RCVD 9-18-25 O/C RO REASSESS DAMAGES TO $38,493.85 7-21-26 O/C RO REASSESS DAMAGES TO $35,235.20 4-22-26 O/C RO REASSESS DAMAGES TO $29,124.44 10-14-25 O/C TO REASSESS DAMAGES TO $23,920.08 3-7-25 | W13: Brentwood Boro | X13: =IFERROR(VLOOKUP(W13,'Transfer Tax'!$A$14:$H$400,8,FALSE),"") | Z13: =IF(OR(Y13="",X13=""),"",Y13*'Transfer Tax'!$B$6*X13) | AE13: 2026-10-25
A14: 95NOV26 | B14: GD-24-011416 | C14: 1061 Bank Street | D14: Bridgeville | E14: 15017 | F14: Bridgeville | G14: 322-G-230 | H14: 0322-G-00230-0000-00 | I14: Residential / unspecified | J14: Tax lien (Sci Fa sur tax lien) | K14: Individual | L14: Cawley, Matthew | M14: BOROUGH OF BRIDGEVILLE | N14: GOEHRING RUTTER & BOEHM | O14: 24361.38 | Q14: 24361.38 | S14: ✔ ✔ – ✔ | T14: Sheriff OK box checked | V14: OK TO SELL 11/2/26 | W14: Bridgeville Boro | X14: =IFERROR(VLOOKUP(W14,'Transfer Tax'!$A$14:$H$400,8,FALSE),"") | Z14: =IF(OR(Y14="",X14=""),"",Y14*'Transfer Tax'!$B$6*X14) | AE14: 2026-10-25
A15: 104NOV26 | B15: GD-22-007750 | C15: 741 Bluff Street | D15: Bridgeville | E15: 15017 | F15: Bridgeville | G15: 255-L-228 | H15: 0255-L-00228-0000-00 | I15: Residential / unspecified | J15: Tax lien (Sci Fa sur tax lien) | K15: Individual | L15: Hersh, Jamison | M15: BRIDGEVILLE BOROUGH | N15: GOEHRING RUTTER & BOEHM | O15: 17246.19 | Q15: 17246.19 | S15: ✔ ✔ – ✔ | T15: Sheriff OK box checked | V15: OK TO SELL 11/2/26 | W15: Bridgeville Boro | X15: =IFERROR(VLOOKUP(W15,'Transfer Tax'!$A$14:$H$400,8,FALSE),"") | Z15: =IF(OR(Y15="",X15=""),"",Y15*'Transfer Tax'!$B$6*X15) | AE15: 2026-10-25
A16: 49NOV26 | B16: MG-26-000215 | C16: 333 Thomas St | D16: Carnegie | E16: 15106 | F16: Carnegie | G16: 104-R-236 | H16: 0104-R-00236-0000-00 | I16: Residential / unspecified | J16: Mortgage foreclosure | K16: Individual | L16: Augustin, Mario Dean | M16: New American Funding LLC | N16: FEIN SUCH KAHN & SHEPARD | O16: 3718.93 | Q16: 3718.93 | S16: ✔ ✔ – ✔ | T16: Sheriff OK box checked | V16: OK TO SELL 11/2/26 | W16: Carnegie Boro | X16: =IFERROR(VLOOKUP(W16,'Transfer Tax'!$A$14:$H$400,8,FALSE),"") | Z16: =IF(OR(Y16="",X16=""),"",Y16*'Transfer Tax'!$B$6*X16) | AE16: 2026-10-25
A17: 98SEP26 | B17: MG-25-001016 | C17: 204 Saxonwald Lane | D17: Pittsburgh | E17: 15234 | F17: Castle Shannon | G17: 190-P-208-6 | H17: search by address | I17: Condominium | J17: Mortgage foreclosure | K17: Individual | L17: Novelli, Ryan | M17: Citizens Bank N.A. | N17: BROCK & SCOTT PLLC | O17: 2430.86 | Q17: 2430.86 | S17: ✔ ✔ ✔ ✔ | T17: Sheriff OK box checked | V17: OK TO SELL 11-2-26 | W17: Castle Shannon Boro | X17: =IFERROR(VLOOKUP(W17,'Transfer Tax'!$A$14:$H$400,8,FALSE),"") | Z17: =IF(OR(Y17="",X17=""),"",Y17*'Transfer Tax'!$B$6*X17) | AE17: 2026-10-25
A18: 113JUL26 | B18: GD-24-009514 | C18: 1102 Gary Ave | D18: Clairton | E18: 15025 | F18: Clairton | G18: 879-J-111 | H18: 0879-J-00111-0000-00 | I18: Residential / unspecified | J18: Tax lien (Sci Fa sur tax lien) | K18: Individual | L18: NIKLAS JR, DAVID A. | M18: County of Allegheny | N18: GOEHRING RUTTER & BOEHM | O18: 27435.33 | P18: 7600 | Q18: 7600 | S18: ✔ ✔ ✔ ✔ | T18: Sheriff OK box checked | U18: Free & clear court order, min bid $7,600.00 | V18: OK TO SELL 11-2-26 F/C O/C FOR A MIN BID OF $7,600.00 | W18: Clairton City | X18: =IFERROR(VLOOKUP(W18,'Transfer Tax'!$A$14:$H$400,8,FALSE),"") | Z18: =IF(OR(Y18="",X18=""),"",Y18*'Transfer Tax'!$B$6*X18) | AE18: 2026-10-25
A19: 22OCT26 | B19: MG-24-000540 | C19: 100 Scott Way | D19: Carnegie | E19: 15106 | F19: Collier | G19: 147-F-34 | H19: 0147-F-00034-0000-00 | I19: Residential / unspecified | J19: Mortgage foreclosure | K19: Individual | L19: Mulligan, Patrick J. | M19: Midfirst Bank | N19: KML LAW GROUP | O19: 26281.37 | Q19: 26281.37 | S19: ✔ ✔ ✔ ✔ | T19: Sheriff OK box checked | V19: OK TO SELL 11-2-26 | W19: Collier Twp | X19: =IFERROR(VLOOKUP(W19,'Transfer Tax'!$A$14:$H$400,8,FALSE),"") | Z19: =IF(OR(Y19="",X19=""),"",Y19*'Transfer Tax'!$B$6*X19) | AE19: 2026-10-25
A20: 145NOV26 | B20: GD-25-013374 | C20: 30 Elmwood St | D20: Pittsburgh | E20: 15205 | F20: Crafton | G20: 39-B-282 | H20: 0039-B-00282-0000-00 | I20: Residential / unspecified | J20: Tax lien (Sci Fa sur tax lien) | K20: Individual | L20: Corcoran, Gloria D. | M20: Borough of Crafton | N20: GOEHRING RUTTER & BOEHM | O20: 57841.47 | Q20: 57841.47 | S20: ✔ ✔ – ✔ | T20: Sheriff OK box checked | V20: OK TO SELL 11/2/26 | W20: Crafton Boro | X20: =IFERROR(VLOOKUP(W20,'Transfer Tax'!$A$14:$H$400,8,FALSE),"") | Z20: =IF(OR(Y20="",X20=""),"",Y20*'Transfer Tax'!$B$6*X20) | AE20: 2026-10-25
A21: 134NOV26 | B21: MG-26-000008 | C21: 90 Dinsmore Avenue | D21: Pittsburgh | E21: 15205 | F21: Crafton | G21: 40-N-121 | H21: 0040-N-00121-0000-00 | I21: Residential / unspecified | J21: Mortgage foreclosure | K21: Individual | L21: Lukaszewicz, Debora | M21: Wells Fargo Bank N.A. | N21: BROCK & SCOTT PLLC | O21: 4982.21 | Q21: 4982.21 | S21: ✔ ✔ – ✔ | T21: Sheriff OK box checked | V21: OK TO SELL 11/2/26 | W21: Crafton Boro | X21: =IFERROR(VLOOKUP(W21,'Transfer Tax'!$A$14:$H$400,8,FALSE),"") | Z21: =IF(OR(Y21="",X21=""),"",Y21*'Transfer Tax'!$B$6*X21) | AE21: 2026-10-25
A22: 77NOV26 | B22: GD-24-010617 | C22: 1057 Crest Dr | D22: Crescent | E22: 15046 | F22: Crescent | G22: 811-F-380 | H22: 0811-F-00380-0000-00 | I22: Residential / unspecified | J22: Tax lien (Sci Fa sur tax lien) | K22: Individual | L22: Miller, Tim | M22: Crescent Township | N22: WEISS BURKARDT KRAMER LLC | O22: 130186.34 | Q22: 130186.34 | S22: ✔ ✔ – ✔ | T22: Sheriff OK box checked | V22: OK TO SELL 11/2/26 | W22: Crescent Twp | X22: =IFERROR(VLOOKUP(W22,'Transfer Tax'!$A$14:$H$400,8,FALSE),"") | Z22: =IF(OR(Y22="",X22=""),"",Y22*'Transfer Tax'!$B$6*X22) | AE22: 2026-10-25
A23: 86SEP26 | B23: MG-25-000402 | C23: 963 Harper Rd | D23: Crescent | E23: 15046 | F23: Crescent | G23: 811-B-216 | H23: 0811-B-00216-0000-00 | I23: Residential / unspecified | J23: Mortgage foreclosure | K23: Individual | L23: Clapperton, Benjamin W. | M23: Freedom Mortgage Corporation | N23: ORLANS PC | O23: 3267.87 | Q23: 3267.87 | R23: 252986.21 | S23: ✔ ✔ ✔ ✔ | T23: Sheriff OK box checked | V23: RCVD O/C TO REASSESS DAMAGES $252,986.21 OK TO SELL 11-2-26 | W23: Crescent Twp | X23: =IFERROR(VLOOKUP(W23,'Transfer Tax'!$A$14:$H$400,8,FALSE),"") | Z23: =IF(OR(Y23="",X23=""),"",Y23*'Transfer Tax'!$B$6*X23) | AE23: 2026-10-25
A24: 34NOV26 | B24: GD-22-011463 | C24: 423 Hillview Street | D24: Duquesne | E24: 15110 | F24: Duquesne | G24: 305-M-78 | H24: 0305-M-00078-0000-00 | I24: Residential / unspecified | J24: Tax lien (Sci Fa sur tax lien) | K24: Individual | L24: Hill, Sherri L | M24: Duquesne City School District | N24: KRATZENBERG & LAZZARO | O24: 57324.9 | Q24: 57324.9 | S24: ✔ ✔ – ✔ | T24: Sheriff OK box checked | V24: OK TO SELL 11/2/26 | W24: Duquesne City | X24: =IFERROR(VLOOKUP(W24,'Transfer Tax'!$A$14:$H$400,8,FALSE),"") | Z24: =IF(OR(Y24="",X24=""),"",Y24*'Transfer Tax'!$B$6*X24) | AE24: 2026-10-25
A25: 34SEP26 | B25: MG-24-000023 | C25: 160 Lincoln Hall Road | D25: Elizabeth | E25: 15037 | F25: Elizabeth Twp | G25: 1130-D-138 | H25: 1130-D-00138-0000-00 | I25: Residential / unspecified | J25: Mortgage foreclosure | K25: Individual | L25: Miller, Jonathan M. | M25: Lakeview Loan Servicing LLC | N25: ORLANS PC | O25: 4210.85 | Q25: 4210.85 | S25: ✔ ✔ ✔ ✔ | T25: Sheriff OK box checked | V25: PLEASE PROVIDE PP LETTER (3129.3 FOR THE NEXT SHERIFF SALE IS NOT A PP LETTER AND WILL NOT BE ACCEPTED, ANY PHYSICAL 3129.3 WE RECEIVE IS A $50 R&I CHARGE) PLEASE UPLOAD ALL FUTURE 3129.3 TO THE ATTORNEY PORTAL OK TO SELL 11-2-26 | W25: Elizabeth Twp | X25: =IFERROR(VLOOKUP(W25,'Transfer Tax'!$A$14:$H$400,8,FALSE),"") | Z25: =IF(OR(Y25="",X25=""),"",Y25*'Transfer Tax'!$B$6*X25) | AE25: 2026-10-25
A26: 115JUL26 | B26: GD-19-011837 | C26: 404 Park Ave | D26: Elizabeth | E26: 15037 | F26: Elizabeth Twp | G26: 1132-L-254 | H26: 1132-L-00254-0000-00 | I26: Residential / unspecified | J26: Tax lien (Sci Fa sur tax lien) | K26: Individual | L26: Detwiler, Mary Jane | M26: County of Allegheny | N26: GOEHRING RUTTER & BOEHM | O26: 61329.1 | P26: 7800 | Q26: 7800 | S26: ✔ ✔ ✔ ✔ | T26: Sheriff OK box checked | U26: Free & clear court order, min bid $7,800.00 Prior winning bidder forfeited (property re-offered) | V26: OK TO SELL 11-2-26 FORFEITED 10/5/26 F/C O/C FOR A MIN BID OF $7,800.00 | W26: Elizabeth Twp | X26: =IFERROR(VLOOKUP(W26,'Transfer Tax'!$A$14:$H$400,8,FALSE),"") | Z26: =IF(OR(Y26="",X26=""),"",Y26*'Transfer Tax'!$B$6*X26) | AE26: 2026-10-25
A27: 32NOV26 | B27: MG-25-000719 | C27: 304 Pappan Dr | D27: Imperial | E27: 15126 | F27: Findlay | G27: 801-L-34 | H27: 0801-L-00034-0000-00 | I27: Residential / unspecified | J27: Mortgage foreclosure | K27: Individual | L27: GREEN, SABRINA M. | M27: Midfirst Bank | N27: PURCELL KRUG & HALLER | O27: 4045.77 | Q27: 4045.77 | S27: ✔ ✔ – ✔ | T27: Sheriff OK box checked | V27: OK TO SELL 11/2/26 | W27: Findlay Twp | X27: =IFERROR(VLOOKUP(W27,'Transfer Tax'!$A$14:$H$400,8,FALSE),"") | Z27: =IF(OR(Y27="",X27=""),"",Y27*'Transfer Tax'!$B$6*X27) | AE27: 2026-10-25
A28: 147NOV26 | B28: GD-25-007632 | C28: 4018 Greensburg Pike | D28: Pittsburgh | E28: 15221 | F28: Forest Hills | G28: 372-P-54 | H28: 0372-P-00054-0000-00 | I28: Residential / unspecified | J28: Tax lien (Sci Fa sur tax lien) | K28: Individual | L28: Stratiff, David J. | M28: Woodland Hills School District | N28: GOEHRING RUTTER & BOEHM | O28: 27434.66 | Q28: 27434.66 | S28: ✔ ✔ – ✔ | T28: Sheriff OK box checked | V28: OK TO SELL 11/2/26 | W28: Forest Hills Boro | X28: =IFERROR(VLOOKUP(W28,'Transfer Tax'!$A$14:$H$400,8,FALSE),"") | Z28: =IF(OR(Y28="",X28=""),"",Y28*'Transfer Tax'!$B$6*X28) | AE28: 2026-10-25
A29: 110NOV26 | B29: MG-26-000588 | C29: 711 Vermont Avenue | D29: Glassport | E29: 15045 | F29: Glassport | G29: 558-G-273 | H29: 0558-G-00273-0000-00 | I29: Residential / unspecified | J29: Mortgage foreclosure | K29: Individual | L29: Koroly, Michael P | M29: U.S. Bank National Association | N29: PURCELL KRUG & HALLER | O29: 3031.99 | Q29: 3031.99 | S29: ✔ ✔ – ✔ | T29: Sheriff OK box checked | U29: FHA-insured loan | V29: FHA OK TO SELL 11/2/26 | W29: Glassport Boro | X29: =IFERROR(VLOOKUP(W29,'Transfer Tax'!$A$14:$H$400,8,FALSE),"") | Z29: =IF(OR(Y29="",X29=""),"",Y29*'Transfer Tax'!$B$6*X29) | AE29: 2026-10-25
A30: 125NOV26 | B30: GD-14-021137 | C30: 36 Rich Hill Road | D30: Cheswick | E30: 15024 | F30: Harmar | G30: 623-C-30 | H30: 0623-C-00030-0000-00 | I30: Residential / unspecified | J30: Tax lien (Sci Fa sur tax lien) | K30: Individual | L30: Smiesko, Lisa A | M30: County Of Allegheny | N30: GOEHRING RUTTER & BOEHM | O30: 66060.68 | Q30: 66060.68 | S30: ✔ ✔ – ✔ | T30: Sheriff OK box checked | V30: OK TO SELL 11/2/26 | W30: Harmar Twp | X30: =IFERROR(VLOOKUP(W30,'Transfer Tax'!$A$14:$H$400,8,FALSE),"") | Z30: =IF(OR(Y30="",X30=""),"",Y30*'Transfer Tax'!$B$6*X30) | AE30: 2026-10-25
A31: 42APR26 | B31: GD-25-011355 | C31: 214 Burwick Court | D31: Pittsburgh | E31: 15238 | F31: Indiana | G31: 835-A-1 | H31: 0835-A-00001-0000-00 | I31: Residential / unspecified | J31: Mortgage foreclosure | K31: Individual | L31: Grimsley, Douglas M. | M31: Federal Home Loan Mortgage Corporation | N31: ROBERTSON ANSCHUTZ SCHNEID | O31: 4766.99 | Q31: 4766.99 | R31: 169975.36 | S31: ✔ ✔ ✔ ✔ | T31: Sheriff OK box checked | V31: OK TO SELL 11-2-26 O/C TO REASSESS DAMAGES TO $169,975.36 | W31: Indiana Twp | X31: =IFERROR(VLOOKUP(W31,'Transfer Tax'!$A$14:$H$400,8,FALSE),"") | Z31: =IF(OR(Y31="",X31=""),"",Y31*'Transfer Tax'!$B$6*X31) | AE31: 2026-10-25
A32: 6NOV26 | B32: GD-24-005281 | C32: 124 Wray Large Road | D32: Clairton | E32: 15025 | F32: Jefferson Hills | G32: 659-C-186 | H32: 0659-C-00186-0000-00 | I32: Residential / unspecified | J32: Tax lien (Sci Fa sur tax lien) | K32: Individual | L32: Killen, Albert J. | M32: West Jefferson Hills School District | N32: WEISS BURKARDT KRAMER LLC | O32: 65779.59 | Q32: 65779.59 | S32: ✔ ✔ – ✔ | T32: Sheriff OK box checked | V32: OK TO SELL 11/2/26 | W32: Jefferson Hills Boro | X32: =IFERROR(VLOOKUP(W32,'Transfer Tax'!$A$14:$H$400,8,FALSE),"") | Z32: =IF(OR(Y32="",X32=""),"",Y32*'Transfer Tax'!$B$6*X32) | AE32: 2026-10-25
A33: 5NOV26 | B33: GD-25-001437 | C33: 2017 Ridge Road | D33: Finleyville | E33: 15332 | F33: Jefferson Hills | G33: 1136-B-216 | H33: 1136-B-00216-0000-00 | I33: Residential / unspecified | J33: Tax lien (Sci Fa sur tax lien) | K33: Individual | L33: Kinneer, David | M33: West Jefferson Hills School District | N33: WEISS BURKARDT KRAMER LLC | O33: 34615.99 | Q33: 34615.99 | S33: ✔ ✔ – ✔ | T33: Sheriff OK box checked | V33: OK TO SELL 11/2/26 | W33: Jefferson Hills Boro | X33: =IFERROR(VLOOKUP(W33,'Transfer Tax'!$A$14:$H$400,8,FALSE),"") | Z33: =IF(OR(Y33="",X33=""),"",Y33*'Transfer Tax'!$B$6*X33) | AE33: 2026-10-25
A34: 18JAN26 | B34: GD-25-002385 | C34: 3069 Scotia Hollow Road | D34: West Elizabeth | E34: 15088 | F34: Jefferson Hills | G34: 1134-M-150 | H34: 1134-M-00150-0000-00 | I34: Residential / unspecified | J34: Tax lien (Sci Fa sur tax lien) | K34: Individual | L34: Plants, David G. | M34: Jefferson Hills Borough | N34: MAIELLO BRUNGO & MAIELLO | O34: 43283.67 | P34: 7000 | Q34: 7000 | S34: ✔ ✔ ✔ ✔ | T34: Sheriff OK box checked | U34: Free & clear court order, min bid $7,000.00 | V34: OK TO SELL 11-2-26 F/C O/C FOR A MIN BID OF $7,000.00 | W34: Jefferson Hills Boro | X34: =IFERROR(VLOOKUP(W34,'Transfer Tax'!$A$14:$H$400,8,FALSE),"") | Z34: =IF(OR(Y34="",X34=""),"",Y34*'Transfer Tax'!$B$6*X34) | AE34: 2026-10-25
A35: 92NOV26 | B35: GD-25-004770 | C35: 28 Victory Lane | D35: Leetsdale | E35: 15056 | F35: Leetsdale | G35: 704-L-163 | H35: 0704-L-00163-0000-00 | I35: Residential / unspecified | J35: Tax lien (Sci Fa sur tax lien) | K35: Individual | L35: Wytiaz, Barbara | M35: Quaker Valley School District | N35: GOEHRING RUTTER & BOEHM | O35: 11985.17 | Q35: 11985.17 | S35: ✔ ✔ – ✔ | T35: Sheriff OK box checked | V35: OK TO SELL 11/2/26 | W35: Leetsdale Boro | X35: =IFERROR(VLOOKUP(W35,'Transfer Tax'!$A$14:$H$400,8,FALSE),"") | Z35: =IF(OR(Y35="",X35=""),"",Y35*'Transfer Tax'!$B$6*X35) | AE35: 2026-10-25
A36: 81NOV26 | B36: GD-26-000638 | C36: 160 Mount Pleasant Rd | D36: Warrendale | E36: 15086 | F36: Marshall | G36: 1999-B-6 | H36: 1999-B-00006-0000-00 | I36: Residential / unspecified | J36: Mortgage foreclosure | K36: Individual | L36: Halpin III, Charles A.J. | M36: Citizens Bank N.A. | N36: GREGORY JAVARDIAN ESQ | O36: 8579.56 | Q36: 8579.56 | S36: ✔ ✔ – ✔ | T36: Sheriff OK box checked | V36: OK TO SELL 11/2/26 | W36: Marshall Twp | X36: =IFERROR(VLOOKUP(W36,'Transfer Tax'!$A$14:$H$400,8,FALSE),"") | Z36: =IF(OR(Y36="",X36=""),"",Y36*'Transfer Tax'!$B$6*X36) | AE36: 2026-10-25
A37: 22JUN26 | B37: MG-25-000865 | C37: 324 Catherine Street | D37: Mckees Rocks | E37: 15136 | F37: McKees Rocks | G37: 74-R-21 | H37: 0074-R-00021-0000-00 | I37: Residential / unspecified | J37: Mortgage foreclosure | K37: Individual | L37: Taravella, Divauna | M37: Citibank N.A. | N37: ROBERTSON ANSCHUTZ SCHNEID | O37: 9606.04 | Q37: 9606.04 | R37: 56990.25 | S37: ✔ ✔ ✔ ✔ | T37: Sheriff OK box checked | U37: Prior winning bidder forfeited (property re-offered) | V37: OK TO SELL 11-2-26 FORFEITED 10/5/26 O/C TO RE-ASSESS DAMAGES TO $56,990.25 RCVD 9/4/26 | W37: McKees Rocks Boro | X37: =IFERROR(VLOOKUP(W37,'Transfer Tax'!$A$14:$H$400,8,FALSE),"") | Z37: =IF(OR(Y37="",X37=""),"",Y37*'Transfer Tax'!$B$6*X37) | AE37: 2026-10-25
A38: 61NOV26 | B38: MG-26-000208 | C38: 709 Latrobe Street Street | D38: Mckeesport | E38: 15133 | F38: McKees Rocks | G38: 465-L-273 | H38: 0465-L-00273-0000-00 | I38: Residential / unspecified | J38: Mortgage foreclosure | K38: Individual | L38: Karpeal, Jacob P | M38: Pennymac Loan Services LLC | N38: POWERS KIRN LLC | O38: 1889.3 | Q38: 1889.3 | S38: ✔ ✔ – ✔ | T38: Sheriff OK box checked | V38: OK TO SELL 11/2/26 | W38: McKees Rocks Boro | X38: =IFERROR(VLOOKUP(W38,'Transfer Tax'!$A$14:$H$400,8,FALSE),"") | Z38: =IF(OR(Y38="",X38=""),"",Y38*'Transfer Tax'!$B$6*X38) | AE38: 2026-10-25
A39: 73OCT26 | B39: GD-23-002702 | C39: 817 Boquet St | D39: Mc Kees Rocks | E39: 15136 | F39: McKees Rocks | G39: 43-E-170 | H39: 0043-E-00170-0000-00 | I39: Residential / unspecified | J39: Tax lien (Sci Fa sur tax lien) | K39: Estate / heirs / trust | L39: Trautman Admin of Estate Joan Trautman, Ronald | M39: McKees Rocks Borough | N39: GOEHRING RUTTER & BOEHM | O39: 30916.14 | Q39: 30916.14 | S39: ✔ ✔ ✔ ✔ | T39: Sheriff OK box checked | V39: OK TO SELL 11/2/26 | W39: McKees Rocks Boro | X39: =IFERROR(VLOOKUP(W39,'Transfer Tax'!$A$14:$H$400,8,FALSE),"") | Z39: =IF(OR(Y39="",X39=""),"",Y39*'Transfer Tax'!$B$6*X39) | AE39: 2026-10-25
A40: 88NOV26 | B40: GD-23-011031 | C40: 207 Erie St | D40: Mc Keesport | E40: 15132 | F40: McKeesport | G40: 308-F-72 | H40: 0308-F-00072-0000-00 | I40: Residential / unspecified | J40: Tax lien (Sci Fa sur tax lien) | K40: Individual | L40: Thomas, Julian | M40: City of McKeesport | N40: KRATZENBERG & LAZZARO | O40: 24077.56 | Q40: 24077.56 | S40: ✔ ✔ – ✔ | T40: Sheriff OK box checked | V40: OK TO SELL 11/2/26 | W40: McKeesport City | X40: =IFERROR(VLOOKUP(W40,'Transfer Tax'!$A$14:$H$400,8,FALSE),"") | Z40: =IF(OR(Y40="",X40=""),"",Y40*'Transfer Tax'!$B$6*X40) | AE40: 2026-10-25
A41: 6MAY26 | B41: MG-25-000627 | C41: 121 Lippert St | D41: Pittsburgh | E41: 15209 | F41: Millvale | G41: 118-P-70 | H41: 0118-P-00070-0000-00 | I41: Residential / unspecified | J41: Mortgage foreclosure | K41: Individual | L41: Callos, David William | M41: Wilmington Savings Fund Society FSB | N41: ROBERTSON ANSCHUTZ SCHNEID | O41: 6071.64 | Q41: 6071.64 | R41: 229568.47 | S41: ✔ ✔ ✔ ✔ | T41: Sheriff OK box checked | V41: OK TO SELL 11-2-26 RCVD O/C ON 10-13-26 TO REASSESS DAMAGES TO $229,568.47 | W41: Millvale Boro | X41: =IFERROR(VLOOKUP(W41,'Transfer Tax'!$A$14:$H$400,8,FALSE),"") | Z41: =IF(OR(Y41="",X41=""),"",Y41*'Transfer Tax'!$B$6*X41) | AE41: 2026-10-25
A42: 51JUL26 | B42: GD-25-007832 | C42: 125 Shoup Street | D42: Pittsburgh | E42: 15209 | F42: Millvale | G42: 79-L-144 | H42: 0079-L-00144-0000-00 | I42: Residential / unspecified | J42: Tax lien (Sci Fa sur tax lien) | K42: Individual | L42: Schmitt, Edward | M42: County of Allegheny | N42: GOEHRING RUTTER & BOEHM | O42: 36837.55 | Q42: 36837.55 | S42: ✔ ✔ ✔ ✔ | T42: Sheriff OK box checked | V42: OK TO SELL 11-2-26 | W42: Millvale Boro | X42: =IFERROR(VLOOKUP(W42,'Transfer Tax'!$A$14:$H$400,8,FALSE),"") | Z42: =IF(OR(Y42="",X42=""),"",Y42*'Transfer Tax'!$B$6*X42) | AE42: 2026-10-25
A43: 3NOV26 | B43: GD-17-006494 | C43: 2239 Tilbrook Rd | D43: Monroeville | E43: 15146 | F43: Monroeville | G43: 746-G-187 | H43: 0746-G-00187-0000-00 | I43: Residential / unspecified | J43: Tax lien (Sci Fa sur tax lien) | K43: Individual | L43: Conroy, Anna Mae | M43: Gateway School District | N43: WEISS BURKARDT KRAMER LLC | O43: 65842.8 | Q43: 65842.8 | S43: ✔ ✔ – ✔ | T43: Sheriff OK box checked | V43: OK TO SELL 11/2/26 | W43: Monroeville Municipality | X43: =IFERROR(VLOOKUP(W43,'Transfer Tax'!$A$14:$H$400,8,FALSE),"") | Z43: =IF(OR(Y43="",X43=""),"",Y43*'Transfer Tax'!$B$6*X43) | AE43: 2026-10-25
A44: 76NOV26 | B44: MG-23-000860 | C44: 405 College Park Drive | D44: Monroeville | E44: 15146 | F44: Monroeville | G44: 976-H-58 | H44: 0976-H-00058-0000-00 | I44: Residential / unspecified | J44: Mortgage foreclosure | K44: Individual | L44: Berkebile, Richard K | M44: Wilmington Savings Fund Society FSB | N44: HILL WALLACK LLP | O44: 8495.75 | Q44: 8495.75 | S44: ✔ ✔ – ✔ | T44: Sheriff OK box checked | V44: OK TO SELL 11/2/26 | W44: Monroeville Municipality | X44: =IFERROR(VLOOKUP(W44,'Transfer Tax'!$A$14:$H$400,8,FALSE),"") | Z44: =IF(OR(Y44="",X44=""),"",Y44*'Transfer Tax'!$B$6*X44) | AE44: 2026-10-25
A45: 7NOV26 | B45: MG-26-000444 | C45: 810 Sweetleaf Drive | D45: Monroeville | E45: 15146 | F45: Monroeville | G45: 742-A-233 | H45: 0742-A-00233-0000-00 | I45: Residential / unspecified | J45: Mortgage foreclosure | K45: Individual | L45: Cozze-Corbett, Samantha | M45: First National Bank of Pennsylvania | N45: GRENEN & BIRSIC P.C. | O45: 2374.2 | Q45: 2374.2 | S45: ✔ ✔ – ✔ | T45: Sheriff OK box checked | V45: OK TO SELL 11/2/26 | W45: Monroeville Municipality | X45: =IFERROR(VLOOKUP(W45,'Transfer Tax'!$A$14:$H$400,8,FALSE),"") | Z45: =IF(OR(Y45="",X45=""),"",Y45*'Transfer Tax'!$B$6*X45) | AE45: 2026-10-25
A46: 107NOV26 | B46: GD-25-008125 | C46: 219 Wyngate Rd | D46: Coraopolis | E46: 15108 | F46: Moon | G46: 598-E-238 | H46: 0598-E-00238-0000-00 | I46: Residential / unspecified | J46: Tax lien (Sci Fa sur tax lien) | K46: Estate / heirs / trust | L46: Unknown Successor Trustees of the House Family Trust | M46: Moon Township | N46: GOEHRING RUTTER & BOEHM | O46: 15614.37 | Q46: 15614.37 | S46: ✔ ✔ – ✔ | T46: Sheriff OK box checked | V46: OK TO SELL 11/2/26 | W46: Moon Twp | X46: =IFERROR(VLOOKUP(W46,'Transfer Tax'!$A$14:$H$400,8,FALSE),"") | Z46: =IF(OR(Y46="",X46=""),"",Y46*'Transfer Tax'!$B$6*X46) | AE46: 2026-10-25
A47: 19NOV26 | B47: MG-19-001316 | C47: 246 Ashland Avenue | D47: Pittsburgh | E47: 15228 | F47: Mount Lebanon | G47: 141-P-48 | H47: 0141-P-00048-0000-00 | I47: Residential / unspecified | J47: Mortgage foreclosure | K47: Individual | L47: Pilarski, Elizabeth E | M47: U.S. Bank Trust National Association | N47: LOGS LEGAL GROUP LLC | O47: 32120.13 | Q47: 32120.13 | S47: ✔ ✔ – ✔ | T47: Sheriff OK box checked | V47: OK TO SELL 11/2/26 | W47: Mount Lebanon Municipality | X47: =IFERROR(VLOOKUP(W47,'Transfer Tax'!$A$14:$H$400,8,FALSE),"") | Z47: =IF(OR(Y47="",X47=""),"",Y47*'Transfer Tax'!$B$6*X47) | AE47: 2026-10-25
A48: 30NOV26 | B48: MG-26-000438 | C48: 709 Pinoak Road | D48: Pittsburgh | E48: 15243 | F48: Mount Lebanon | G48: 99-N-320 | H48: 0099-N-00320-0000-00 | I48: Residential / unspecified | J48: Mortgage foreclosure | K48: Individual | L48: Schofield Jr., Richard E | M48: Dollar Bank Federal Savings Bank | N48: GRENEN & BIRSIC P.C. | O48: 28596.48 | Q48: 28596.48 | S48: ✔ ✔ – ✔ | T48: Sheriff OK box checked | V48: OK TO SELL 11/2/26 | W48: Mount Lebanon Municipality | X48: =IFERROR(VLOOKUP(W48,'Transfer Tax'!$A$14:$H$400,8,FALSE),"") | Z48: =IF(OR(Y48="",X48=""),"",Y48*'Transfer Tax'!$B$6*X48) | AE48: 2026-10-25
A49: 35NOV26 | B49: MG-26-000100 | C49: 871 Valleyview Road | D49: Pittsburgh | E49: 15243 | F49: Mount Lebanon | G49: 99-J-100 | H49: 0099-J-00100-0000-00 | I49: Residential / unspecified | J49: Mortgage foreclosure | K49: Individual | L49: Prendergast, John M | M49: Farmers National Bank of Canfield | N49: LYNN KING & SCHREFFLER | O49: 20635.04 | Q49: 20635.04 | S49: ✔ ✔ – ✔ | T49: Sheriff OK box checked | V49: OK TO SELL 11/2/26 | W49: Mount Lebanon Municipality | X49: =IFERROR(VLOOKUP(W49,'Transfer Tax'!$A$14:$H$400,8,FALSE),"") | Z49: =IF(OR(Y49="",X49=""),"",Y49*'Transfer Tax'!$B$6*X49) | AE49: 2026-10-25
A50: 142NOV26 | B50: GD-26-002371 | C50: 1608 Arlington Ave | D50: Pittsburgh | E50: 15210 | F50: Mount Oliver | G50: 14-L-260 | H50: 0014-L-00260-0000-00 | I50: Residential / unspecified | J50: Tax lien (Sci Fa sur tax lien) | K50: Individual | L50: Garrett, Nancy | M50: Mt. Oliver Borough | N50: KRATZENBERG & LAZZARO | O50: 20517.18 | Q50: 20517.18 | S50: ✔ ✔ – ✔ | T50: Sheriff OK box checked | V50: OK TO SELL 11/2/26 | W50: Mount Oliver Boro | X50: =IFERROR(VLOOKUP(W50,'Transfer Tax'!$A$14:$H$400,8,FALSE),"") | Z50: =IF(OR(Y50="",X50=""),"",Y50*'Transfer Tax'!$B$6*X50) | AE50: 2026-10-25
A51: 72JUL26 | B51: GD-24-007323 | C51: 150 East Virginia Avenue | D51: Homestead | E51: 15120 | F51: Munhall | G51: 132-S-194 | H51: 0132-S-00194-0000-00 | I51: Residential / unspecified | J51: Tax lien (Sci Fa sur tax lien) | K51: Individual | L51: Willie, Theresa | M51: County of Allegheny | N51: GOEHRING RUTTER & BOEHM | O51: 28591.22 | Q51: 28591.22 | S51: ✔ ✔ ✔ ✔ | T51: Sheriff OK box checked | V51: OK TO SELL 11-2-26 | W51: Munhall Boro | X51: =IFERROR(VLOOKUP(W51,'Transfer Tax'!$A$14:$H$400,8,FALSE),"") | Z51: =IF(OR(Y51="",X51=""),"",Y51*'Transfer Tax'!$B$6*X51) | AE51: 2026-10-25
A52: 22SEP26 | B52: GD-26-000602 | C52: 700 E 17th Ave | D52: Homestead | E52: 15120 | F52: Munhall | G52: 131-D-333 | H52: 0131-D-00333-0000-00 | I52: Residential / unspecified | J52: Mortgage foreclosure | K52: Entity (LLC/LP/Inc) | L52: ENK Real Estate Investments LLC | M52: U.S. Bank Trust Company National Association | N52: FRIEDMAN VARTOLO LLP | O52: 5687.19 | Q52: 5687.19 | R52: 177189.64 | S52: ✔ ✔ ✔ ✔ | T52: Sheriff OK box checked | V52: OK TO SELL 11-2-26 O/C TO REASSESS DAMAGES TO $177,189.64 | W52: Munhall Boro | X52: =IFERROR(VLOOKUP(W52,'Transfer Tax'!$A$14:$H$400,8,FALSE),"") | Z52: =IF(OR(Y52="",X52=""),"",Y52*'Transfer Tax'!$B$6*X52) | AE52: 2026-10-25
A53: 99NOV26 | B53: GD-24-004866 | C53: 1753 Wolfe Avenue | D53: Braddock | E53: 15104 | F53: North Braddock | G53: 375-F-324 | H53: 0375-F-00324-0000-00 | I53: Residential / unspecified | J53: Tax lien (Sci Fa sur tax lien) | K53: Individual | L53: Perez, Amado Justo | M53: Woodland Hills School District | N53: GOEHRING RUTTER & BOEHM | O53: 25408.18 | Q53: 25408.18 | S53: ✔ ✔ – ✔ | T53: Sheriff OK box checked | V53: OK TO SELL 11/2/26 | W53: North Braddock Boro | X53: =IFERROR(VLOOKUP(W53,'Transfer Tax'!$A$14:$H$400,8,FALSE),"") | Z53: =IF(OR(Y53="",X53=""),"",Y53*'Transfer Tax'!$B$6*X53) | AE53: 2026-10-25
A54: 26SEP26 | B54: MG-26-000185 | C54: 108 Tintsman Ave | D54: North Versailles | E54: 15137 | F54: North Versailles | G54: 456-S-280 | H54: 0456-S-00280-0000-00 | I54: Residential / unspecified | J54: Mortgage foreclosure | K54: Individual | L54: GIBALA, SANDRA L. | M54: Huntington National Bank | N54: MANLEY DEAS KOCHALSKI LLC | O54: 11852.24 | Q54: 11852.24 | S54: ✔ ✔ ✔ ✔ | T54: Sheriff OK box checked | U54: Prior winning bidder forfeited (property re-offered) | V54: MUST RECALCULATE OPENING BID PRIOR TO SALE...NEW 10/5/26 C+T BID $9631.35 OK TO SELL 11-2-26 FORFEITED 10% 9-8-26 | W54: North Versailles Twp | X54: =IFERROR(VLOOKUP(W54,'Transfer Tax'!$A$14:$H$400,8,FALSE),"") | Z54: =IF(OR(Y54="",X54=""),"",Y54*'Transfer Tax'!$B$6*X54) | AE54: 2026-10-25
A55: 141NOV26 | B55: GD-24-000653 | C55: 1209 Lincoln Hwy | D55: North Versailles | E55: 15137 | F55: North Versailles | G55: 644-N-376 | H55: 0644-N-00376-0000-00 | I55: Residential / unspecified | J55: Tax lien (Sci Fa sur tax lien) | K55: Individual | L55: Evanuik, James | M55: East Allegheny School District | N55: KRATZENBERG & LAZZARO | O55: 70994.23 | Q55: 70994.23 | S55: ✔ ✔ – ✔ | T55: Sheriff OK box checked | V55: OK TO SELL 11/2/26 | W55: North Versailles Twp | X55: =IFERROR(VLOOKUP(W55,'Transfer Tax'!$A$14:$H$400,8,FALSE),"") | Z55: =IF(OR(Y55="",X55=""),"",Y55*'Transfer Tax'!$B$6*X55) | AE55: 2026-10-25
A56: 59JUL26 | B56: GD-25-008194 | C56: 516 Vincent Street | D56: North Versailles | E56: 15137 | F56: North Versailles | G56: 456-L-234 | H56: 0456-L-00234-0000-00 | I56: Residential / unspecified | J56: Tax lien (Sci Fa sur tax lien) | K56: Individual | L56: Zubasic, Jesse Scott | M56: COUNTY OF ALLEGHENY | N56: GOEHRING RUTTER & BOEHM | O56: 17858.63 | P56: 7600 | Q56: 7600 | S56: ✔ ✔ ✔ ✔ | T56: Sheriff OK box checked | U56: Free & clear court order, min bid $7,600.00 | V56: OK TO SELL 11-2-26 F/C O/C FOR A MIN BID OF $7,600.00 | W56: North Versailles Twp | X56: =IFERROR(VLOOKUP(W56,'Transfer Tax'!$A$14:$H$400,8,FALSE),"") | Z56: =IF(OR(Y56="",X56=""),"",Y56*'Transfer Tax'!$B$6*X56) | AE56: 2026-10-25
A57: 70OCT26 | B57: GD-25-008114 | C57: 520 Westinghouse Avenue | D57: North Versailles | E57: 15137 | F57: North Versailles | G57: 459-F-225 | H57: 0459-F-00225-0000-00 | I57: Residential / unspecified | J57: Tax lien (Sci Fa sur tax lien) | K57: Individual | L57: Parkinson, Miguel R. | M57: County of Allegheny | N57: GOEHRING RUTTER & BOEHM | O57: 9195.11 | Q57: 9195.11 | S57: ✔ ✔ ✔ ✔ | T57: Sheriff OK box checked | V57: OK TO SELL 11/2/26 | W57: North Versailles Twp | X57: =IFERROR(VLOOKUP(W57,'Transfer Tax'!$A$14:$H$400,8,FALSE),"") | Z57: =IF(OR(Y57="",X57=""),"",Y57*'Transfer Tax'!$B$6*X57) | AE57: 2026-10-25
A58: 40OCT26 | B58: MG-25-000986 | C58: 1002 Powers Run Rd | D58: Pittsburgh | E58: 15238 | F58: O'Hara | G58: 291-C-66 | H58: 0291-C-00066-0000-00 | I58: Residential / unspecified | J58: Mortgage foreclosure | K58: Individual | L58: Stephens, Kathleen Louise | M58: U.S. Bank National Association | N58: HLADIK ONORATO AND FEDERMAN LLP | O58: 2306.37 | Q58: 2306.37 | R58: 75763.34 | S58: ✔ ✔ ✔ ✔ | T58: Sheriff OK box checked | V58: OK TO SELL 11-2-26 RCVD O/C TO REASSESS DAMAGES TO $75,763.34 | W58: O'Hara Twp | X58: =IFERROR(VLOOKUP(W58,'Transfer Tax'!$A$14:$H$400,8,FALSE),"") | Z58: =IF(OR(Y58="",X58=""),"",Y58*'Transfer Tax'!$B$6*X58) | AE58: 2026-10-25
A59: 123NOV26 | B59: GD-25-007439 | C59: 147 Oakhurst Road | D59: Pittsburgh | E59: 15215 | F59: O'Hara | G59: 224-E-44 | H59: 0224-E-00044-0000-00 | I59: Residential / unspecified | J59: Tax lien (Sci Fa sur tax lien) | K59: Individual | L59: Depasquale, Severino C | M59: O'Hara Township | N59: GOEHRING RUTTER & BOEHM | O59: 21840.24 | Q59: 21840.24 | S59: ✔ ✔ – ✔ | T59: Sheriff OK box checked | V59: OK TO SELL 11/2/26 | W59: O'Hara Twp | X59: =IFERROR(VLOOKUP(W59,'Transfer Tax'!$A$14:$H$400,8,FALSE),"") | Z59: =IF(OR(Y59="",X59=""),"",Y59*'Transfer Tax'!$B$6*X59) | AE59: 2026-10-25
A60: 103SEP26 | B60: GD-25-007653 | C60: 400 Woodland Ave | D60: Oakmont | E60: 15139 | F60: Oakmont | G60: 362-G-151 | H60: 0362-G-00151-0000-00 | I60: Residential / unspecified | J60: Tax lien (Sci Fa sur tax lien) | K60: Entity (LLC/LP/Inc) | L60: Scottsdale Rei LLC | M60: Riverview School District | N60: MAIELLO BRUNGO & MAIELLO | O60: 40576.6 | Q60: 40576.6 | S60: ✔ ✔ ✔ ✔ | T60: Sheriff OK box checked | U60: Prior winning bidder forfeited (property re-offered) | V60: OK TO SELL 11-2-26 FORFEITED 11-2-26 | W60: Oakmont Boro | X60: =IFERROR(VLOOKUP(W60,'Transfer Tax'!$A$14:$H$400,8,FALSE),"") | Z60: =IF(OR(Y60="",X60=""),"",Y60*'Transfer Tax'!$B$6*X60) | AE60: 2026-10-25
A61: 84AUG26 | B61: GD-23-011285 | C61: 800 Valley St | D61: Oakmont | E61: 15139 | F61: Oakmont | G61: 363-S-253 | H61: 0363-S-00253-0000-00 | I61: Residential / unspecified | J61: Tax lien (Sci Fa sur tax lien) | K61: Entity (LLC/LP/Inc) | L61: HP Property Pro LLC | M61: Riverview School District | N61: MAIELLO BRUNGO & MAIELLO | O61: 34708.2 | Q61: 34708.2 | S61: ✔ ✔ ✔ ✔ | T61: Sheriff OK box checked | V61: OK TO SELL 11-2-26 | W61: Oakmont Boro | X61: =IFERROR(VLOOKUP(W61,'Transfer Tax'!$A$14:$H$400,8,FALSE),"") | Z61: =IF(OR(Y61="",X61=""),"",Y61*'Transfer Tax'!$B$6*X61) | AE61: 2026-10-25
A62: 60NOV26 | B62: MG-25-000322 | C62: 219 Richland Drive | D62: Pittsburgh | E62: 15235 | F62: Penn Hills | G62: 370-H-24 | H62: 0370-H-00024-0000-00 | I62: Residential / unspecified | J62: Mortgage foreclosure | K62: Individual | L62: THORN III, William F. | M62: PennyMac Loan Services LLC | N62: POWERS KIRN LLC | O62: 1684.28 | Q62: 1684.28 | S62: ✔ ✔ – ✔ | T62: Sheriff OK box checked | V62: OK TO SELL 11/2/26 | W62: Penn Hills Municipality | X62: =IFERROR(VLOOKUP(W62,'Transfer Tax'!$A$14:$H$400,8,FALSE),"") | Z62: =IF(OR(Y62="",X62=""),"",Y62*'Transfer Tax'!$B$6*X62) | AE62: 2026-10-25
A63: 12JUN26 | B63: GD-25-004752 | C63: 255 Almar Dr | D63: Verona | E63: 15147 | F63: Penn Hills | G63: 447-P-207 | H63: 0447-P-00207-0000-00 | I63: Residential / unspecified | J63: Mortgage foreclosure | K63: Individual | L63: HALPIN III, Charles A.J. | M63: Select Portfolio Servicing Inc. | N63: GREGORY JAVARDIAN ESQ | O63: 4211.85 | Q63: 4211.85 | S63: ✔ ✔ ✔ ✔ | T63: Sheriff OK box checked | V63: OK TO SELL 11-2-26 | W63: Penn Hills Municipality | X63: =IFERROR(VLOOKUP(W63,'Transfer Tax'!$A$14:$H$400,8,FALSE),"") | Z63: =IF(OR(Y63="",X63=""),"",Y63*'Transfer Tax'!$B$6*X63) | AE63: 2026-10-25
A64: 53OCT26 | B64: GD-24-008177 | C64: 52 Everett Road | D64: Pittsburgh | E64: 15235 | F64: Penn Hills | G64: 173-S-47 | H64: 0173-S-00047-0000-00 | I64: Residential / unspecified | J64: Tax lien (Sci Fa sur tax lien) | K64: Individual | L64: Beasley, Karen P. | M64: County of Allegheny | N64: GOEHRING RUTTER & BOEHM | O64: 19540.69 | Q64: 19540.69 | S64: ✔ ✔ ✔ ✔ | T64: Sheriff OK box checked | V64: OK TO SELL 11/2/26 | W64: Penn Hills Municipality | X64: =IFERROR(VLOOKUP(W64,'Transfer Tax'!$A$14:$H$400,8,FALSE),"") | Z64: =IF(OR(Y64="",X64=""),"",Y64*'Transfer Tax'!$B$6*X64) | AE64: 2026-10-25
A65: 18AUG26 | B65: GD-23-012860 | C65: 631 National Dr | D65: Pittsburgh | E65: 15235 | F65: Penn Hills | G65: 537-E-249 | H65: 0537-E-00249-0000-00 | I65: Residential / unspecified | J65: Tax lien (Sci Fa sur tax lien) | K65: Individual | L65: Bentley, Anthony | M65: Penn Hills School District | N65: MAIELLO BRUNGO & MAIELLO | O65: 36873.68 | Q65: 36873.68 | S65: ✔ ✔ ✔ ✔ | T65: Sheriff OK box checked | V65: OK TO SELL 11-2-26 | W65: Penn Hills Municipality | X65: =IFERROR(VLOOKUP(W65,'Transfer Tax'!$A$14:$H$400,8,FALSE),"") | Z65: =IF(OR(Y65="",X65=""),"",Y65*'Transfer Tax'!$B$6*X65) | AE65: 2026-10-25
A66: 80NOV26 | B66: GD-25-011270 | C66: 944 6th Street | D66: Verona | E66: 15147 | F66: Penn Hills | G66: 445-A-266 | H66: 0445-A-00266-0000-00 | I66: Residential / unspecified | J66: Mortgage foreclosure | K66: Individual | L66: Christian, Dolores | M66: Carrington Mortgage Services LLC | N66: GREGORY JAVARDIAN ESQ | O66: 1889.3 | Q66: 1889.3 | S66: ✔ ✔ – ✔ | T66: Sheriff OK box checked | V66: OK TO SELL 11/2/26 | W66: Penn Hills Municipality | X66: =IFERROR(VLOOKUP(W66,'Transfer Tax'!$A$14:$H$400,8,FALSE),"") | Z66: =IF(OR(Y66="",X66=""),"",Y66*'Transfer Tax'!$B$6*X66) | AE66: 2026-10-25
A67: 140NOV26 | B67: GD-26-005350 | C67: 932 Park Place | D67: Wexford | E67: 15090 | F67: Pine | G67: 1658-H-46 | H67: 1658-H-00046-0000-00 | I67: Residential / unspecified | J67: Mortgage foreclosure | K67: Individual | L67: Unger, Ruth Ann | M67: Wilmington Savings Fund Society FSB | N67: HILL WALLACK LLP | O67: 1914.47 | Q67: 1914.47 | R67: 175104.21 | S67: ✔ ✔ – ✔ | T67: Sheriff OK box checked | V67: OK TO SELL 11/2/26 RCVD O/C TO REASSESS DAMAGES TO $175,104.21 | W67: Pine Twp | X67: =IFERROR(VLOOKUP(W67,'Transfer Tax'!$A$14:$H$400,8,FALSE),"") | Z67: =IF(OR(Y67="",X67=""),"",Y67*'Transfer Tax'!$B$6*X67) | AE67: 2026-10-25
A68: 109NOV26 | B68: GD-25-004329 | C68: 115 Brinton Ave | D68: Pitcairn | E68: 15140 | F68: Pitcairn | G68: 747-B-12 | H68: 0747-B-00012-0000-00 | I68: Residential / unspecified | J68: Tax lien (Sci Fa sur tax lien) | K68: Entity (LLC/LP/Inc) | L68: R2 Property Group LLC | M68: Pitcairn Borough | N68: GOEHRING RUTTER & BOEHM | O68: 13851.74 | Q68: 13851.74 | S68: ✔ ✔ – ✔ | T68: Sheriff OK box checked | V68: OK TO SELL 11/2/26 | W68: Pitcairn Boro | X68: =IFERROR(VLOOKUP(W68,'Transfer Tax'!$A$14:$H$400,8,FALSE),"") | Z68: =IF(OR(Y68="",X68=""),"",Y68*'Transfer Tax'!$B$6*X68) | AE68: 2026-10-25
A69: 44NOV26 | B69: MG-25-001073 | C69: 801 Brinton Ave | D69: Pitcairn | E69: 15140 | F69: Pitcairn | G69: 746-R-179 | H69: 0746-R-00179-0000-00 | I69: Residential / unspecified | J69: Mortgage foreclosure | K69: Individual | L69: TRKULA, JAMES | M69: MidFirst Bank | N69: MANLEY DEAS KOCHALSKI LLC | O69: 3555.7 | Q69: 3555.7 | S69: ✔ ✔ – ✔ | T69: Sheriff OK box checked | U69: FHA-insured loan | V69: FHA OK TO SELL 11/2/26 | W69: Pitcairn Boro | X69: =IFERROR(VLOOKUP(W69,'Transfer Tax'!$A$14:$H$400,8,FALSE),"") | Z69: =IF(OR(Y69="",X69=""),"",Y69*'Transfer Tax'!$B$6*X69) | AE69: 2026-10-25
A70: 37OCT26 | B70: GD-24-000634 | C70: 1108 High St | D70: Pittsburgh | E70: 15212 | F70: Pittsburgh | G70: 24-B-229 | H70: 0024-B-00229-0000-00 | I70: Residential / unspecified | J70: Mortgage foreclosure | K70: Entity (LLC/LP/Inc) | L70: S & T Investment LLC | M70: Reigo by Meitav Dash US Investments, LLC | N70: GINGO PALUMBO LAW GROUP | O70: 6563.46 | Q70: 6563.46 | S70: ✔ ✔ ✔ ✔ | T70: Sheriff OK box checked | V70: OK TO SELL 11-2-26 | W70: Pittsburgh City (Pittsburgh SD) | X70: =IFERROR(VLOOKUP(W70,'Transfer Tax'!$A$14:$H$400,8,FALSE),"") | Z70: =IF(OR(Y70="",X70=""),"",Y70*'Transfer Tax'!$B$6*X70) | AE70: 2026-10-25
A71: 63NOV26 | B71: MG-25-001093 | C71: 1226 Denisonview Street ; Denisonview Street | D71: Pittsburgh | E71: 15205 | F71: Pittsburgh | G71: 19-J-230 ; 19-N-210 ; 19-N-211 | H71: 0019-J-00230-0000-00 ; 0019-N-00210-0000-00 ; 0019-N-00211-0000-00 | I71: Residential / unspecified ; Vacant Land | J71: Mortgage foreclosure | K71: Individual | L71: Logsdon, Christine M | M71: Pennsylvania Housing Finance Agency | N71: PURCELL KRUG & HALLER | O71: 3451.97 | Q71: 3451.97 | S71: ✔ ✔ – ✔ | T71: Sheriff OK box checked | V71: OK TO SELL 11/2/26 | W71: Pittsburgh City (Pittsburgh SD) | X71: =IFERROR(VLOOKUP(W71,'Transfer Tax'!$A$14:$H$400,8,FALSE),"") | Z71: =IF(OR(Y71="",X71=""),"",Y71*'Transfer Tax'!$B$6*X71) | AE71: 2026-10-25
A72: 149NOV26 | B72: GD-26-005514 | C72: 130 E Meyers St | D72: Pittsburgh | E72: 15210 | F72: Pittsburgh | G72: 60-H-198 | H72: 0060-H-00198-0000-00 | I72: Residential / unspecified | J72: Tax lien (Sci Fa sur tax lien) | K72: Estate / heirs / trust | L72: Unknown Heirs of Matilda C. Brennan | M72: County of Allegheny | N72: GOEHRING RUTTER & BOEHM | O72: 22363.09 | Q72: 22363.09 | S72: ✔ ✔ – ✔ | T72: Sheriff OK box checked | U72: Court decree on file | V72: DECREE OK TO SELL 11/2/26 | W72: Pittsburgh City (Pittsburgh SD) | X72: =IFERROR(VLOOKUP(W72,'Transfer Tax'!$A$14:$H$400,8,FALSE),"") | Z72: =IF(OR(Y72="",X72=""),"",Y72*'Transfer Tax'!$B$6*X72) | AE72: 2026-10-25
A73: 21NOV26 | B73: MG-22-000697 | C73: 1569 Summerdale St ; Margaret Street | D73: Pittsburgh | E73: 15204 | F73: Pittsburgh | G73: 71-K-197 ; 71-K-244 ; 71-K-199 | H73: 0071-K-00197-0000-00 ; 0071-K-00244-0000-00 ; 0071-K-00199-0000-00 | I73: Vacant Land ; Residential / unspecified | J73: Mortgage foreclosure | K73: Individual | L73: HESS, JUDITH | M73: U.S. Bank National Association | N73: LOGS LEGAL GROUP LLC | O73: 8628.91 | Q73: 8628.91 | S73: ✔ ✔ – ✔ | T73: Sheriff OK box checked | V73: OK TO SELL 11/2/26 | W73: Pittsburgh City (Pittsburgh SD) | X73: =IFERROR(VLOOKUP(W73,'Transfer Tax'!$A$14:$H$400,8,FALSE),"") | Z73: =IF(OR(Y73="",X73=""),"",Y73*'Transfer Tax'!$B$6*X73) | AE73: 2026-10-25
A74: 151NOV26 | B74: GD-26-005512 | C74: 1922 Westmont Ave | D74: Pittsburgh | E74: 15210 | F74: Pittsburgh | G74: 60-R-237 | H74: 0060-R-00237-0000-00 | I74: Residential / unspecified | J74: Tax lien (Sci Fa sur tax lien) | K74: Estate / heirs / trust | L74: Unknown Heirs of Pauline Lejeune | M74: County of Allegheny | N74: GOEHRING RUTTER & BOEHM | O74: 43150.47 | Q74: 43150.47 | S74: ✔ ✔ – ✔ | T74: Sheriff OK box checked | U74: Court decree on file | V74: DECREE OK TO SELL 11/2/26 | W74: Pittsburgh City (Pittsburgh SD) | X74: =IFERROR(VLOOKUP(W74,'Transfer Tax'!$A$14:$H$400,8,FALSE),"") | Z74: =IF(OR(Y74="",X74=""),"",Y74*'Transfer Tax'!$B$6*X74) | AE74: 2026-10-25
A75: 71NOV26 | B75: MG-26-000179 | C75: 207 Fordyce Street | D75: Pittsburgh | E75: 15210 | F75: Pittsburgh | G75: 34-H-311 | H75: 0034-H-00311-0000-00 | I75: Residential / unspecified | J75: Mortgage foreclosure | K75: Individual | L75: Link, Jared M. | M75: Rocket Mortgage LLC | N75: BROCK & SCOTT PLLC | O75: 4133.06 | Q75: 4133.06 | S75: ✔ ✔ – ✔ | T75: Sheriff OK box checked | V75: OK TO SELL 11/2/26 | W75: Pittsburgh City (Pittsburgh SD) | X75: =IFERROR(VLOOKUP(W75,'Transfer Tax'!$A$14:$H$400,8,FALSE),"") | Z75: =IF(OR(Y75="",X75=""),"",Y75*'Transfer Tax'!$B$6*X75) | AE75: 2026-10-25
A76: 150NOV26 | B76: GD-26-005370 | C76: 2285 Valera Ave | D76: Pittsburgh | E76: 15210 | F76: Pittsburgh | G76: 95-L-29 | H76: 0095-L-00029-0000-00 | I76: Residential / unspecified | J76: Tax lien (Sci Fa sur tax lien) | K76: Individual | L76: Metzger, Mathilda | M76: County of Allegheny | N76: GOEHRING RUTTER & BOEHM | O76: 68460.82 | Q76: 68460.82 | S76: ✔ ✔ – ✔ | T76: Sheriff OK box checked | U76: Court decree on file | V76: DECREE OK TO SELL 11/2/26 | W76: Pittsburgh City (Pittsburgh SD) | X76: =IFERROR(VLOOKUP(W76,'Transfer Tax'!$A$14:$H$400,8,FALSE),"") | Z76: =IF(OR(Y76="",X76=""),"",Y76*'Transfer Tax'!$B$6*X76) | AE76: 2026-10-25
A77: 152NOV26 | B77: GD-26-005510 | C77: 232 Nobles Ln | D77: Pittsburgh | E77: 15210 | F77: Pittsburgh | G77: 60-A-270 | H77: 0060-A-00270-0000-00 | I77: Residential / unspecified | J77: Tax lien (Sci Fa sur tax lien) | K77: Estate / heirs / trust | L77: Oakridge Asset Property Trust | M77: County of Allegheny | N77: GOEHRING RUTTER & BOEHM | O77: 18563.47 | Q77: 18563.47 | S77: ✔ ✔ – ✔ | T77: Sheriff OK box checked | U77: Court decree on file | V77: DECREE OK TO SELL 11/2/26 | W77: Pittsburgh City (Pittsburgh SD) | X77: =IFERROR(VLOOKUP(W77,'Transfer Tax'!$A$14:$H$400,8,FALSE),"") | Z77: =IF(OR(Y77="",X77=""),"",Y77*'Transfer Tax'!$B$6*X77) | AE77: 2026-10-25
A78: 148NOV26 | B78: GD-26-005372 | C78: 232 Zara St | D78: Pittsburgh | E78: 15210 | F78: Pittsburgh | G78: 14-P-93 | H78: 0014-P-00093-0000-00 | I78: Residential / unspecified | J78: Tax lien (Sci Fa sur tax lien) | K78: Entity (LLC/LP/Inc) | L78: Ustvrea LLC | M78: County of Allegheny | N78: GOEHRING RUTTER & BOEHM | O78: 31281.9 | Q78: 31281.9 | S78: ✔ ✔ – ✔ | T78: Sheriff OK box checked | U78: Court decree on file | V78: DECREE OK TO SELL 11/2/26 | W78: Pittsburgh City (Pittsburgh SD) | X78: =IFERROR(VLOOKUP(W78,'Transfer Tax'!$A$14:$H$400,8,FALSE),"") | Z78: =IF(OR(Y78="",X78=""),"",Y78*'Transfer Tax'!$B$6*X78) | AE78: 2026-10-25
A79: 155NOV26 | B79: GD-26-005513 | C79: 27 Minooka St | D79: Pittsburgh | E79: 15210 | F79: Pittsburgh | G79: 60-B-104 | H79: 0060-B-00104-0000-00 | I79: Residential / unspecified | J79: Tax lien (Sci Fa sur tax lien) | K79: Estate / heirs / trust | L79: Unknown Heirs of John F. Wierzchowski | M79: County of Allegheny | N79: GOEHRING RUTTER & BOEHM | O79: 29714.87 | Q79: 29714.87 | S79: ✔ ✔ – ✔ | T79: Sheriff OK box checked | U79: Court decree on file | V79: DECREE OK TO SELL 11/2/26 304 96 30 0 430 | W79: Pittsburgh City (Pittsburgh SD) | X79: =IFERROR(VLOOKUP(W79,'Transfer Tax'!$A$14:$H$400,8,FALSE),"") | Z79: =IF(OR(Y79="",X79=""),"",Y79*'Transfer Tax'!$B$6*X79) | AE79: 2026-10-25
A80: 66SEP26 | B80: MG-26-000148 | C80: 2716 Burham Street | D80: Pittsburgh | E80: 15203 | F80: Pittsburgh | G80: 13-H-21 | H80: 0013-H-00021-0000-00 | I80: Residential / unspecified | J80: Mortgage foreclosure | K80: Individual | L80: Richards, Jon | M80: HSBC Bank USA N.A. | N80: ROBERTSON ANSCHUTZ SCHNEID | O80: 14501.07 | Q80: 14501.07 | S80: ✔ ✔ ✔ ✔ | T80: Sheriff OK box checked | V80: OK TO SELL 11/2/26 | W80: Pittsburgh City (Pittsburgh SD) | X80: =IFERROR(VLOOKUP(W80,'Transfer Tax'!$A$14:$H$400,8,FALSE),"") | Z80: =IF(OR(Y80="",X80=""),"",Y80*'Transfer Tax'!$B$6*X80) | AE80: 2026-10-25
A81: 58NOV26 | B81: MG-26-000405 | C81: 3125 Ashlyn St | D81: Pittsburgh | E81: 15204 | F81: Pittsburgh | G81: 42-L-273 | H81: 0042-L-00273-0000-00 | I81: Residential / unspecified | J81: Mortgage foreclosure | K81: Individual | L81: Fennick, Olivia S. | M81: U.S. Bank Trust National Association | N81: STERN & EISENBERG | O81: 1867.12 | Q81: 1867.12 | S81: ✔ ✔ – ✔ | T81: Sheriff OK box checked | V81: OK TO SELL 11/2/26 | W81: Pittsburgh City (Pittsburgh SD) | X81: =IFERROR(VLOOKUP(W81,'Transfer Tax'!$A$14:$H$400,8,FALSE),"") | Z81: =IF(OR(Y81="",X81=""),"",Y81*'Transfer Tax'!$B$6*X81) | AE81: 2026-10-25
A82: 154NOV26 | B82: GD-26-005367 | C82: 34 Minooka St | D82: Pittsburgh | E82: 15210 | F82: Pittsburgh | G82: 33-P-333 | H82: 0033-P-00333-0000-00 | I82: Residential / unspecified | J82: Tax lien (Sci Fa sur tax lien) | K82: Individual | L82: Carroll, Christopher | M82: County of Allegheny | N82: GOEHRING RUTTER & BOEHM | O82: 20848.3 | Q82: 20848.3 | S82: ✔ ✔ – ✔ | T82: Sheriff OK box checked | U82: Court decree on file | V82: DECREE OK TO SELL 11/2/26 | W82: Pittsburgh City (Pittsburgh SD) | X82: =IFERROR(VLOOKUP(W82,'Transfer Tax'!$A$14:$H$400,8,FALSE),"") | Z82: =IF(OR(Y82="",X82=""),"",Y82*'Transfer Tax'!$B$6*X82) | AE82: 2026-10-25
A83: 56SEP26 | B83: GD-26-002653 | C83: 4022 Oswald Street | D83: Pittsburgh | E83: 15212 | F83: Pittsburgh | G83: 114-K-132 | H83: 0114-K-00132-0000-00 | I83: Residential / unspecified | J83: Mortgage foreclosure | K83: Entity (LLC/LP/Inc) | L83: C&C Linhart LLC | M83: U.S. Bank Trust National Association | N83: HLADIK ONORATO AND FEDERMAN LLP | O83: 1961.72 | Q83: 1961.72 | S83: ✔ ✔ ✔ ✔ | T83: Sheriff OK box checked | V83: OK TO SELL 11-2-26 | W83: Pittsburgh City (Pittsburgh SD) | X83: =IFERROR(VLOOKUP(W83,'Transfer Tax'!$A$14:$H$400,8,FALSE),"") | Z83: =IF(OR(Y83="",X83=""),"",Y83*'Transfer Tax'!$B$6*X83) | AE83: 2026-10-25
A84: 153NOV26 | B84: GD-26-005511 | C84: 416 Arabella St | D84: Pittsburgh | E84: 15210 | F84: Pittsburgh | G84: 33-A-299 | H84: 0033-A-00299-0000-00 | I84: Residential / unspecified | J84: Tax lien (Sci Fa sur tax lien) | K84: Individual | L84: Bonner, Sharon | M84: County of Allegheny | N84: GOEHRING RUTTER & BOEHM | O84: 56179.98 | Q84: 56179.98 | S84: ✔ ✔ – ✔ | T84: Sheriff OK box checked | U84: Court decree on file | V84: DECREE OK TO SELL 11/2/26 | W84: Pittsburgh City (Pittsburgh SD) | X84: =IFERROR(VLOOKUP(W84,'Transfer Tax'!$A$14:$H$400,8,FALSE),"") | Z84: =IF(OR(Y84="",X84=""),"",Y84*'Transfer Tax'!$B$6*X84) | AE84: 2026-10-25
A85: 50NOV26 | B85: MG-18-000394 | C85: 4320 Stanley St | D85: Pittsburgh | E85: 15207 | F85: Pittsburgh | G85: 55-F-135 | H85: 0055-F-00135-0000-00 | I85: Residential / unspecified | J85: Mortgage foreclosure | K85: Individual | L85: MANNION, MARGARET ANN | M85: ATLANTICA, LLC | N85: FEIN SUCH KAHN & SHEPARD | O85: 7901.24 | Q85: 7901.24 | S85: ✔ ✔ – ✔ | T85: Sheriff OK box checked | V85: OK TO SELL 11/2/26 | W85: Pittsburgh City (Pittsburgh SD) | X85: =IFERROR(VLOOKUP(W85,'Transfer Tax'!$A$14:$H$400,8,FALSE),"") | Z85: =IF(OR(Y85="",X85=""),"",Y85*'Transfer Tax'!$B$6*X85) | AE85: 2026-10-25
A86: 99SEP26 | B86: MG-24-000613 | C86: 4942 Rosetta Street | D86: Pittsburgh | E86: 15224 | F86: Pittsburgh | G86: 50-F-102 | H86: 0050-F-00102-0000-00 | I86: Residential / unspecified | J86: Mortgage foreclosure | K86: Individual | L86: Floyd, Frank C. | M86: U.S. Bank National Association | N86: BROCK & SCOTT PLLC | O86: 6236.97 | Q86: 6236.97 | S86: ✔ ✔ ✔ ✔ | T86: Sheriff OK box checked | V86: OK TO SELL 11-2-26 O/C TO REASSESS DAMAGES RCVD ON 9-28-26 TO $33,671.98 | W86: Pittsburgh City (Pittsburgh SD) | X86: =IFERROR(VLOOKUP(W86,'Transfer Tax'!$A$14:$H$400,8,FALSE),"") | Z86: =IF(OR(Y86="",X86=""),"",Y86*'Transfer Tax'!$B$6*X86) | AE86: 2026-10-25
A87: 11NOV26 | B87: MG-26-000373 | C87: 700 Attica Street | D87: Pittsburgh | E87: 15220 | F87: Pittsburgh | G87: 19-D-23 | H87: 0019-D-00023-0000-00 | I87: Residential / unspecified | J87: Mortgage foreclosure | K87: Individual | L87: Kyles, Augusta | M87: Bank of New York Mellon | N87: STERN & EISENBERG | O87: 6739.5 | Q87: 6739.5 | R87: 18682.02 | S87: ✔ ✔ – ✔ | T87: Sheriff OK box checked | V87: OK TO SELL 11/2/26 RCVD O/C TO REASSESS DAMAGES $18,682.02 | W87: Pittsburgh City (Pittsburgh SD) | X87: =IFERROR(VLOOKUP(W87,'Transfer Tax'!$A$14:$H$400,8,FALSE),"") | Z87: =IF(OR(Y87="",X87=""),"",Y87*'Transfer Tax'!$B$6*X87) | AE87: 2026-10-25
A88: 67SEP26 | B88: MG-26-000253 | C88: 713 Gearing Ave | D88: Pittsburgh | E88: 15210 | F88: Pittsburgh | G88: 15-R-261 | H88: 0015-R-00261-0000-00 | I88: Residential / unspecified | J88: Mortgage foreclosure | K88: Individual | L88: Hamilton, Clarence R. | M88: PNC Bank National Association | N88: ROBERTSON ANSCHUTZ SCHNEID | O88: 2016.48 | Q88: 2016.48 | S88: ✔ ✔ ✔ ✔ | T88: Sheriff OK box checked | V88: OK TO SELL 11/2/26 | W88: Pittsburgh City (Pittsburgh SD) | X88: =IFERROR(VLOOKUP(W88,'Transfer Tax'!$A$14:$H$400,8,FALSE),"") | Z88: =IF(OR(Y88="",X88=""),"",Y88*'Transfer Tax'!$B$6*X88) | AE88: 2026-10-25
A89: 54NOV25 | B89: GD-23-011927 | C89: 220 Old Lebanon Church Rd | D89: Pittsburgh | E89: 15236 | F89: Pleasant Hills | G89: 388-K-167 | H89: 0388-K-00167-0000-00 | I89: Residential / unspecified | J89: Tax lien (Sci Fa sur tax lien) | K89: Individual | L89: Slampak, Robert K | M89: West Jefferson Hills School District | N89: WEISS BURKARDT KRAMER LLC | O89: 159211.83 | P89: 25000 | Q89: 25000 | S89: ✔ ✔ ✔ ✔ | T89: Sheriff OK box checked | U89: Free & clear court order, min bid $25,000.00 (earlier orders: $100,000.00) Prior winning bidder forfeited (property re-offered) Opening bid recalculated – new C+T bid $152,696.57 | V89: OK TO SELL 11-2-26 FORFEITED 10/5/26 ($5,600 FORFEITED) FORFEITED 11/3/25 ($6,200 FORFEITED) 11-26-25 OC TO REFUND PURCHASER DESPOSIT F/C O/C FOR A MIN BID OF $25,000.00 (NEW) O/C F/C FOR A MIN BID OF $100,000.00 CALCULATED COST + TAX BID AS OF 10/5/26 $152,696.57-DPI | W89: Pleasant Hills Boro | X89: =IFERROR(VLOOKUP(W89,'Transfer Tax'!$A$14:$H$400,8,FALSE),"") | Z89: =IF(OR(Y89="",X89=""),"",Y89*'Transfer Tax'!$B$6*X89) | AE89: 2026-10-25
A90: 14JUL26 | B90: MG-24-000120 | C90: 4908 Sardis Rd | D90: New Kensington | E90: 15068 | F90: Plum | G90: 968-K-261 | H90: 0968-K-00261-0000-00 | I90: Residential / unspecified | J90: Mortgage foreclosure | K90: Estate / heirs / trust | L90: Unknown Heirs of Daniel Swanger Jr aka Daniel J Swanger Jr | M90: U.S. Bank Trust National Association | N90: FRIEDMAN VARTOLO LLP | O90: 9488.08 | Q90: 9488.08 | R90: 161670.2 | S90: ✔ ✔ ✔ ✔ | T90: Sheriff OK box checked | V90: OK TO SELL 11-2-26 RCVD O/C TO REASSESS DAMAGES $161,670.20 | W90: Plum Boro | X90: =IFERROR(VLOOKUP(W90,'Transfer Tax'!$A$14:$H$400,8,FALSE),"") | Z90: =IF(OR(Y90="",X90=""),"",Y90*'Transfer Tax'!$B$6*X90) | AE90: 2026-10-25
A91: 108NOV26 | B91: GD-25-008525 | C91: 300 Wildflower Court | D91: Pittsburgh | E91: 15202 | F91: Ross | G91: 216-P-104-D | H91: search by address | I91: Residential / unspecified | J91: Tax lien (Sci Fa sur tax lien) | K91: Individual | L91: Brenner, Brittany L. | M91: North Hills School District | N91: GOEHRING RUTTER & BOEHM | O91: 26361.64 | Q91: 26361.64 | S91: ✔ ✔ – ✔ | T91: Sheriff OK box checked | V91: OK TO SELL 11/2/26 | W91: Ross Twp | X91: =IFERROR(VLOOKUP(W91,'Transfer Tax'!$A$14:$H$400,8,FALSE),"") | Z91: =IF(OR(Y91="",X91=""),"",Y91*'Transfer Tax'!$B$6*X91) | AE91: 2026-10-25
A92: 52JUN26 | B92: MG-24-000994 | C92: 612 Beall Way | D92: Sewickley | E92: 15143 | F92: Sewickley | G92: 421-B-25 | H92: 0421-B-00025-0000-00 | I92: Residential / unspecified | J92: Mortgage foreclosure | K92: Individual | L92: Graham, Eileen | M92: Wilmington Savings Fund Society, FSB | N92: FRIEDMAN VARTOLO LLP | O92: 1980.08 | Q92: 1980.08 | R92: 300036.79 | S92: ✔ ✔ ✔ ✔ | T92: Sheriff OK box checked | V92: OK TO SELL 11-2-26 O/C TO REASSESS DAMAGES TO $300,036.79 | W92: Sewickley Boro | X92: =IFERROR(VLOOKUP(W92,'Transfer Tax'!$A$14:$H$400,8,FALSE),"") | Z92: =IF(OR(Y92="",X92=""),"",Y92*'Transfer Tax'!$B$6*X92) | AE92: 2026-10-25
A93: 4OCT26 | B93: AR-25-009094 | C93: 1400 Smokey Wood Drive Unit 609 | D93: Pittsburgh | E93: 15218 | F93: Swissvale | G93: 234-P-165-3609 | H93: search by address | I93: Condominium | J93: HOA / condo assessment judgment | K93: Estate / heirs / trust | L93: Unknown Heirs of Vincent Catalano | M93: Forest Condominium Association | N93: BRANDT MILNES & REA P. C. | O93: 11158.93 | Q93: 11158.93 | S93: ✔ ✔ ✔ ✔ | T93: Sheriff OK box checked | U93: HOA/condo judgment sale — a first mortgage may survive the sale | V93: OK TO SELL 11/2/26 | W93: Swissvale Boro | X93: =IFERROR(VLOOKUP(W93,'Transfer Tax'!$A$14:$H$400,8,FALSE),"") | Z93: =IF(OR(Y93="",X93=""),"",Y93*'Transfer Tax'!$B$6*X93) | AE93: 2026-10-25
A94: 98NOV26 | B94: GD-25-005661 | C94: 2016 Monongahela Ave | D94: Pittsburgh | E94: 15218 | F94: Swissvale | G94: 178-G-140 | H94: 0178-G-00140-0000-00 | I94: Residential / unspecified | J94: Tax lien (Sci Fa sur tax lien) | K94: Individual | L94: Mobit, Isaiah A | M94: Woodland Hills School District | N94: GOEHRING RUTTER & BOEHM | O94: 14492.45 | Q94: 14492.45 | S94: ✔ ✔ – ✔ | T94: Sheriff OK box checked | V94: OK TO SELL 11/2/26 | W94: Swissvale Boro | X94: =IFERROR(VLOOKUP(W94,'Transfer Tax'!$A$14:$H$400,8,FALSE),"") | Z94: =IF(OR(Y94="",X94=""),"",Y94*'Transfer Tax'!$B$6*X94) | AE94: 2026-10-25
A95: 98AUG26 | B95: GD-26-000316 | C95: 2213 Woodstock Ave | D95: Pittsburgh | E95: 15218 | F95: Swissvale | G95: 178-H-210 | H95: 0178-H-00210-0000-00 | I95: Residential / unspecified | J95: Mortgage foreclosure | K95: Entity (LLC/LP/Inc) | L95: Lewisbrothers0412 LLC | M95: NWL Company LLC | N95: FRIEDMAN VARTOLO LLP | O95: 2248.85 | Q95: 2248.85 | S95: ✔ ✔ ✔ ✔ | T95: Sheriff OK box checked | V95: OK TO SELL 11-2-26 | W95: Swissvale Boro | X95: =IFERROR(VLOOKUP(W95,'Transfer Tax'!$A$14:$H$400,8,FALSE),"") | Z95: =IF(OR(Y95="",X95=""),"",Y95*'Transfer Tax'!$B$6*X95) | AE95: 2026-10-25
A96: 106NOV26 | B96: GD-22-003481 | C96: 2312 S Braddock Avenue | D96: Pittsburgh | E96: 15218 | F96: Swissvale | G96: 235-E-372 | H96: 0235-E-00372-0000-00 | I96: Residential / unspecified | J96: Tax lien (Sci Fa sur tax lien) | K96: Entity (LLC/LP/Inc) | L96: HP Properties | M96: Woodland Hills School District | N96: GOEHRING RUTTER & BOEHM | O96: 38919.1 | Q96: 38919.1 | S96: ✔ ✔ – ✔ | T96: Sheriff OK box checked | V96: OK TO SELL 11/2/26 | W96: Swissvale Boro | X96: =IFERROR(VLOOKUP(W96,'Transfer Tax'!$A$14:$H$400,8,FALSE),"") | Z96: =IF(OR(Y96="",X96=""),"",Y96*'Transfer Tax'!$B$6*X96) | AE96: 2026-10-25
A97: 143NOV26 | B97: GD-25-009219 | C97: 7471 Delmar Way | D97: Pittsburgh | E97: 15218 | F97: Swissvale | G97: 177-R-292 | H97: 0177-R-00292-0000-00 | I97: Residential / unspecified | J97: Tax lien (Sci Fa sur tax lien) | K97: Individual | L97: Stonebraker, Kathleen J. | M97: Borough of Swissvale | N97: KRATZENBERG & LAZZARO | O97: 145809.04 | Q97: 145809.04 | S97: ✔ ✔ – ✔ | T97: Sheriff OK box checked | V97: OK TO SELL 11/2/26 | W97: Swissvale Boro | X97: =IFERROR(VLOOKUP(W97,'Transfer Tax'!$A$14:$H$400,8,FALSE),"") | Z97: =IF(OR(Y97="",X97=""),"",Y97*'Transfer Tax'!$B$6*X97) | AE97: 2026-10-25
A98: 94NOV26 | B98: GD-24-011356 | C98: 106 6th St | D98: Turtle Creek | E98: 15145 | F98: Turtle Creek | G98: 456-H-19 | H98: 0456-H-00019-0000-00 | I98: Residential / unspecified | J98: Tax lien (Sci Fa sur tax lien) | K98: Individual | L98: Gallagher, Brian E. | M98: Woodland Hills School District | N98: GOEHRING RUTTER & BOEHM | O98: 16567.27 | Q98: 16567.27 | S98: ✔ ✔ – ✔ | T98: Sheriff OK box checked | V98: OK TO SELL 11/2/26 | W98: Turtle Creek Boro | X98: =IFERROR(VLOOKUP(W98,'Transfer Tax'!$A$14:$H$400,8,FALSE),"") | Z98: =IF(OR(Y98="",X98=""),"",Y98*'Transfer Tax'!$B$6*X98) | AE98: 2026-10-25
A99: 138NOV26 | B99: MG-26-000464 | C99: 125 8th Street | D99: Turtle Creek | E99: 15145 | F99: Turtle Creek | G99: 456-C-42 | H99: 0456-C-00042-0000-00 | I99: Residential / unspecified | J99: Mortgage foreclosure | K99: Individual | L99: Grande, Dominick | M99: Pennsylvania Housing Finance Agency | N99: VITTI LAW GROUP INC | O99: 2650.34 | Q99: 2650.34 | S99: ✔ ✔ – ✔ | T99: Sheriff OK box checked | V99: OK TO SELL 11/2/26 | W99: Turtle Creek Boro | X99: =IFERROR(VLOOKUP(W99,'Transfer Tax'!$A$14:$H$400,8,FALSE),"") | Z99: =IF(OR(Y99="",X99=""),"",Y99*'Transfer Tax'!$B$6*X99) | AE99: 2026-10-25
A100: 105NOV26 | B100: GD-22-013934 | C100: 1311 Maple Ave | D100: Turtle Creek | E100: 15145 | F100: Turtle Creek | G100: 455-M-153 | H100: 0455-M-00153-0000-00 | I100: Residential / unspecified | J100: Tax lien (Sci Fa sur tax lien) | K100: Individual | L100: Ward, Talise Jones | M100: Woodland Hills School District | N100: GOEHRING RUTTER & BOEHM | O100: 44824.46 | Q100: 44824.46 | S100: ✔ ✔ – ✔ | T100: Sheriff OK box checked | V100: OK TO SELL 11/2/26 | W100: Turtle Creek Boro | X100: =IFERROR(VLOOKUP(W100,'Transfer Tax'!$A$14:$H$400,8,FALSE),"") | Z100: =IF(OR(Y100="",X100=""),"",Y100*'Transfer Tax'!$B$6*X100) | AE100: 2026-10-25
A101: 108OCT26 | B101: MG-24-000905 | C101: 1609 Mobile Avenue | D101: Turtle Creek | E101: 15145 | F101: Turtle Creek | G101: 544-J-84 | H101: 0544-J-00084-0000-00 | I101: Residential / unspecified | J101: Mortgage foreclosure | K101: Individual | L101: Dendy, Araminta Janai | M101: ROCKET MORTGAGE, LLC F/K/A QUICKEN LOANS, LLC | N101: BROCK & SCOTT PLLC | O101: 1952.9 | Q101: 1952.9 | S101: ✔ ✔ ✔ ✔ | T101: Sheriff OK box checked | V101: OK TO SELL 11-2-26 | W101: Turtle Creek Boro | X101: =IFERROR(VLOOKUP(W101,'Transfer Tax'!$A$14:$H$400,8,FALSE),"") | Z101: =IF(OR(Y101="",X101=""),"",Y101*'Transfer Tax'!$B$6*X101) | AE101: 2026-10-25
...

Sheet Almost Ready
A1: Almost Ready — Mon Nov 2
A2: Active residential cases where Service and 3129.2 are done and only Rule 3129.3 is still needed (often filed at the last minute), plus VERIFY cases where the OK box and notes disagree.
A4: Sale ID | B4: Case # | C4: Property address | D4: City | E4: ZIP | F4: Municipality | G4: Parcel ID(s) | H4: County parcel ID (portal format) | I4: Property type | J4: Sale category | K4: Owner type | L4: Defendant / owner | M4: Plaintiff | N4: Plaintiff attorney | O4: Cost & Tax bid | P4: Free & clear min bid | Q4: Opening bid to watch | R4: Reassessed damages (judgment) | S4: Boxes Svs · 3129.2 · 3129.3 · OK | T4: What's still missing | U4: Flags / title & bidding risks | V4: Sheriff comments (verbatim) | W4: Transfer tax municipality | X4: Transfer tax rate (total) | Y4: YOUR ENTRY: Assessed value | Z4: Est. transfer tax on sheriff deed | AA4: YOUR ENTRY: Max bid | AB4: YOUR ENTRY: My notes | AC4: YOUR ENTRY: Sold for | AD4: YOUR ENTRY: Bidder # | AE4: First listed here
A5: 1SEP26 | B5: GD-22-008550 | C5: 221 Walnut St | D5: Pittsburgh | E5: 15238 | F5: Blawnox | G5: 292-N-392 | H5: 0292-N-00392-0000-00 | I5: Residential / unspecified | J5: Tax lien (Sci Fa sur tax lien) | K5: Individual | L5: RABINOWITZ, JACK | M5: Blawnox Borough | N5: KRATZENBERG & LAZZARO | O5: 36807.63 | Q5: 36807.63 | S5: ✔ ✔ – – | T5: Only Rule 3129.3 outstanding • Rule 3129.3 notice of postponed sale date (for 11/2/26) | V5: NEED 3129.3 FOR 11-2-26 | W5: Blawnox Boro | X5: =IFERROR(VLOOKUP(W5,'Transfer Tax'!$A$14:$H$400,8,FALSE),"") | Z5: =IF(OR(Y5="",X5=""),"",Y5*'Transfer Tax'!$B$6*X5) | AE5: 2026-10-25
A6: 62JAN26 | B6: GD-25-003317 | C6: 2086 Smithdale Rd | D6: West Newton | E6: 15089 | F6: Elizabeth Twp | G6: 1732-S-226 | H6: 1732-S-00226-0000-00 | I6: Residential / unspecified | J6: Tax lien (Sci Fa sur tax lien) | K6: Estate / heirs / trust | L6: Unknown Heirs of Urcell Nicholson aka Vienna Ercel Nicholson | M6: Elizabeth Forward School District | N6: MAIELLO BRUNGO & MAIELLO | O6: 15431.56 | Q6: 15431.56 | S6: ✔ ✔ – – | T6: Only Rule 3129.3 outstanding • Rule 3129.3 notice of postponed sale date (for 11/2/26) | V6: NEED 3129.3 FOR 11-2-26 | W6: Elizabeth Twp | X6: =IFERROR(VLOOKUP(W6,'Transfer Tax'!$A$14:$H$400,8,FALSE),"") | Z6: =IF(OR(Y6="",X6=""),"",Y6*'Transfer Tax'!$B$6*X6) | AE6: 2026-10-25
A7: 4SEP26 | B7: GD-24-011990 | C7: 1615 Sumac St | D7: Mc Keesport | E7: 15132 | F7: McKeesport | G7: 381-G-63 | H7: 0381-G-00063-0000-00 | I7: Residential / unspecified | J7: Tax lien (Sci Fa sur tax lien) | K7: Entity (LLC/LP/Inc) | L7: Next Level Development LLC | M7: City of McKeesport | N7: KRATZENBERG & LAZZARO | O7: 44590.13 | Q7: 44590.13 | S7: ✔ ✔ – – | T7: Only Rule 3129.3 outstanding • Rule 3129.3 notice of postponed sale date (for 11/2/26) | V7: NEED 3129.3 FOR 11-2-26 | W7: McKeesport City | X7: =IFERROR(VLOOKUP(W7,'Transfer Tax'!$A$14:$H$400,8,FALSE),"") | Z7: =IF(OR(Y7="",X7=""),"",Y7*'Transfer Tax'!$B$6*X7) | AE7: 2026-10-25
A8: 29OCT26 | B8: MG-26-000156 | C8: 2417 Riverview St | D8: Mc Keesport | E8: 15132 | F8: McKeesport | G8: 381-N-103 | H8: 0381-N-00103-0000-00 | I8: Residential / unspecified | J8: Mortgage foreclosure | K8: Entity (LLC/LP/Inc) | L8: Pittsburg Luxe LLC | M8: Wilmington Savings Fund Society FSB | N8: FRIEDMAN VARTOLO LLP | O8: 2965.14 | Q8: 2965.14 | S8: ✔ ✔ – – | T8: Only Rule 3129.3 outstanding • Rule 3129.3 notice of postponed sale date (for 11/2/26) | V8: NEED 3129.3 FOR 11-2-26 | W8: McKeesport City | X8: =IFERROR(VLOOKUP(W8,'Transfer Tax'!$A$14:$H$400,8,FALSE),"") | Z8: =IF(OR(Y8="",X8=""),"",Y8*'Transfer Tax'!$B$6*X8) | AE8: 2026-10-25
A9: 46JUL26 | B9: MG-26-000026 | C9: 1303 Craigview Drive | D9: Pittsburgh | E9: 15243 | F9: Mount Lebanon | G9: 194-C-131 | H9: 0194-C-00131-0000-00 | I9: Residential / unspecified | J9: Mortgage foreclosure | K9: Individual | L9: Whaley, Martin G. | M9: Wells Fargo Bank National Association | N9: McCalla Raymer Leibert Pierce LLC | O9: 30650.91 | Q9: 30650.91 | S9: ✔ ✔ – – | T9: Only Rule 3129.3 outstanding • Rule 3129.3 notice of postponed sale date – filed copy rejected, must be re-filed | U9: Save Your Home program involvement | V9: CANNOT GO TO SALE ON 11-2-26 CONCILIATION CONFERENCE RESCHEDULED TO 10-23-26 PP TO 10/5/26 FOR DEF TO APPLY FOR THE SAVE YOUR HOME PROGRAM 3129.3 NOT ACCEPTED NEEDS TO HAVE ATTORNEY SIGNATURE AND CONTACT INFORMATION ON EVERY DOCUMENT | W9: Mount Lebanon Municipality | X9: =IFERROR(VLOOKUP(W9,'Transfer Tax'!$A$14:$H$400,8,FALSE),"") | Z9: =IF(OR(Y9="",X9=""),"",Y9*'Transfer Tax'!$B$6*X9) | AE9: 2026-10-25
A10: 5OCT26 | B10: GD-25-013736 | C10: 950 Margaretta Ave | D10: Pittsburgh | E10: 15234 | F10: Mount Lebanon | G10: 250-E-234 | H10: 0250-E-00234-0000-00 | I10: Residential / unspecified | J10: Tax lien (Sci Fa sur tax lien) | K10: Individual | L10: Edwards Realty & Associates L.P. | M10: Mt. Lebanon School District | N10: WEISS BURKARDT KRAMER LLC | O10: 36309.45 | Q10: 36309.45 | S10: ✔ ✔ – – | T10: Only Rule 3129.3 outstanding • Rule 3129.3 notice of postponed sale date (for 11/2/26) | V10: NEED 3129.3 FOR 11-2-26 | W10: Mount Lebanon Municipality | X10: =IFERROR(VLOOKUP(W10,'Transfer Tax'!$A$14:$H$400,8,FALSE),"") | Z10: =IF(OR(Y10="",X10=""),"",Y10*'Transfer Tax'!$B$6*X10) | AE10: 2026-10-25
A11: 3AUG26 | B11: GD-24-014344 | C11: 2429 Perry St | D11: Homestead | E11: 15120 | F11: Munhall | G11: 181-A-218 | H11: 0181-A-00218-0000-00 | I11: Residential / unspecified | J11: Mortgage foreclosure | K11: Entity (LLC/LP/Inc) | L11: 2429 Perry St. LLC | M11: U.S. Bank Trust National Association | N11: ORLANS PC | O11: 6653.5 | Q11: 6653.5 | R11: 219281.18 | S11: ✔ ✔ – – | T11: Only Rule 3129.3 outstanding • Rule 3129.3 notice of postponed sale date (for 11/2/26) | V11: RCVD O/C TO REASSESS DAMAGES $219,281.18 ON 6/24/26 NEED 3129.3 FOR 11-2-26 | W11: Munhall Boro | X11: =IFERROR(VLOOKUP(W11,'Transfer Tax'!$A$14:$H$400,8,FALSE),"") | Z11: =IF(OR(Y11="",X11=""),"",Y11*'Transfer Tax'!$B$6*X11) | AE11: 2026-10-25
A12: 106MAR26 | B12: GD-24-010373 | C12: 606 E 14th Ave | D12: Homestead | E12: 15120 | F12: Munhall | G12: 130-S-267 | H12: 0130-S-00267-0000-00 | I12: Residential / unspecified | J12: Tax lien (Sci Fa sur tax lien) | K12: Individual | L12: Pacelli, Jeanine A. | M12: Borough of Munhall | N12: LEGAL TAX SERVICE | O12: 65577.98 | Q12: 65577.98 | S12: ✔ ✔ ✔ – | T12: VERIFY – Service/3129.2/3129.3 checked, OK not yet checked, no items listed | W12: Munhall Boro | X12: =IFERROR(VLOOKUP(W12,'Transfer Tax'!$A$14:$H$400,8,FALSE),"") | Z12: =IF(OR(Y12="",X12=""),"",Y12*'Transfer Tax'!$B$6*X12) | AE12: 2026-10-25
A13: 47SEP26 | B13: GD-22-012990 | C13: 618 East 9th Avenue | D13: Homestead | E13: 15120 | F13: Munhall | G13: 130-M-143 | H13: 0130-M-00143-0000-00 | I13: Residential / unspecified | J13: Tax lien (Sci Fa sur tax lien) | K13: Individual | L13: Green, Sharifa B. | M13: Munhall Borough | N13: LEGAL TAX SERVICE | O13: 8596.8 | Q13: 8596.8 | S13: ✔ ✔ – – | T13: Only Rule 3129.3 outstanding • Rule 3129.3 notice of postponed sale date (for 11/2/26) | V13: NEED 3129.3 FOR 11-2-26 | W13: Munhall Boro | X13: =IFERROR(VLOOKUP(W13,'Transfer Tax'!$A$14:$H$400,8,FALSE),"") | Z13: =IF(OR(Y13="",X13=""),"",Y13*'Transfer Tax'!$B$6*X13) | AE13: 2026-10-25
A14: 3SEP26 | B14: GD-24-004175 | C14: 14 Greenwich Court | D14: Oakmont | E14: 15139 | F14: Oakmont | G14: 444-K-21-14 | H14: search by address | I14: Residential / unspecified | J14: Tax lien (Sci Fa sur tax lien) | K14: Individual | L14: Grogg, Melynda C | M14: Oakmont Borough | N14: KRATZENBERG & LAZZARO | O14: 20647.81 | Q14: 20647.81 | S14: ✔ ✔ – – | T14: Only Rule 3129.3 outstanding • Rule 3129.3 notice of postponed sale date (for 11/2/26) | V14: NEED 3129.3 FOR 11-2-26 | W14: Oakmont Boro | X14: =IFERROR(VLOOKUP(W14,'Transfer Tax'!$A$14:$H$400,8,FALSE),"") | Z14: =IF(OR(Y14="",X14=""),"",Y14*'Transfer Tax'!$B$6*X14) | AE14: 2026-10-25
A15: 9AUG26 | B15: MG-25-000548 | C15: 154 Glenfield Drive | D15: Pittsburgh | E15: 15235 | F15: Penn Hills | G15: 448-K-114 | H15: 0448-K-00114-0000-00 | I15: Residential / unspecified | J15: Mortgage foreclosure | K15: Individual | L15: Wilhoit II, James R. | M15: Federal Home Loan Mortgage Corporation | N15: LOGS LEGAL GROUP LLC | O15: 2967.49 | Q15: 2967.49 | S15: ✔ ✔ ✔ – | T15: VERIFY – notes say OK TO SELL but OK box unchecked | V15: OK TO SELL 11-2-26 | W15: Penn Hills Municipality | X15: =IFERROR(VLOOKUP(W15,'Transfer Tax'!$A$14:$H$400,8,FALSE),"") | Z15: =IF(OR(Y15="",X15=""),"",Y15*'Transfer Tax'!$B$6*X15) | AE15: 2026-10-25
A16: 57SEP26 | B16: GD-25-013585 | C16: 1234 High Street | D16: Pittsburgh | E16: 15212 | F16: Pittsburgh | G16: 24-C-152 | H16: 0024-C-00152-0000-00 | I16: Residential / unspecified | J16: Mortgage foreclosure | K16: Entity (LLC/LP/Inc) | L16: Mansion Global LLC | M16: EF Mortgage LLC | N16: HLADIK ONORATO AND FEDERMAN LLP | O16: 3826.83 | Q16: 3826.83 | S16: ✔ ✔ – – | T16: Only Rule 3129.3 outstanding • Rule 3129.3 notice of postponed sale date (for 11/2/26) | V16: NEED 3129.3 FOR 11-2-26 | W16: Pittsburgh City (Pittsburgh SD) | X16: =IFERROR(VLOOKUP(W16,'Transfer Tax'!$A$14:$H$400,8,FALSE),"") | Z16: =IF(OR(Y16="",X16=""),"",Y16*'Transfer Tax'!$B$6*X16) | AE16: 2026-10-25
A17: 119JUN25 | B17: GD-24-011281 | C17: 2812 Wadlow St | D17: Pittsburgh | E17: 15212 | F17: Pittsburgh | G17: 45-B-13 | H17: 0045-B-00013-0000-00 | I17: Residential / unspecified | J17: Mortgage foreclosure | K17: Entity (LLC/LP/Inc) | L17: FERRELL HOLDINGS LLC | M17: Athene Annuity and Life Company | N17: FRIEDMAN VARTOLO LLP | O17: 16622.72 | Q17: 16622.72 | R17: 170646.35 | S17: ✔ ✔ – – | T17: Only Rule 3129.3 outstanding • Rule 3129.3 notice of postponed sale date (for 11/2/26) – filed copy rejected, must be re-filed | V17: 3129.3 FOR 11-2-26 NOT ACCEPTED THERE IS NO FILING DATE ON DOCUMENTS (10-22-26) O/C TO REASSESS DAMAGES TO $170,646.35 | W17: Pittsburgh City (Pittsburgh SD) | X17: =IFERROR(VLOOKUP(W17,'Transfer Tax'!$A$14:$H$400,8,FALSE),"") | Z17: =IF(OR(Y17="",X17=""),"",Y17*'Transfer Tax'!$B$6*X17) | AE17: 2026-10-25
A18: 10OCT26 | B18: GD-26-002368 | C18: 2914 Glasgow St | D18: Pittsburgh | E18: 15204 | F18: Pittsburgh | G18: 21-J-186 | H18: 0021-J-00186-0000-00 | I18: Residential / unspecified | J18: Mortgage foreclosure | K18: Entity (LLC/LP/Inc) | L18: Sheraden Redevelopment Group LP | M18: U.S. Bank Trust Company National Association | N18: FRIEDMAN VARTOLO LLP | O18: 1858.7 | Q18: 1858.7 | R18: 177331.16 | S18: ✔ ✔ – – | T18: Only Rule 3129.3 outstanding • Rule 3129.3 notice of postponed sale date (for 11/2/26) | V18: RCVD O/C TO REASSESS DAMAGES $177,331.16 NEED 3129.3 FOR 11-2-26 | W18: Pittsburgh City (Pittsburgh SD) | X18: =IFERROR(VLOOKUP(W18,'Transfer Tax'!$A$14:$H$400,8,FALSE),"") | Z18: =IF(OR(Y18="",X18=""),"",Y18*'Transfer Tax'!$B$6*X18) | AE18: 2026-10-25
A19: 85JUL25 | B19: GD-24-010996 | C19: 1204 Washington Boulevard Rear | D19: Mckeesport | E19: 15133 | F19: Port Vue | G19: 383-G-116 | H19: 0383-G-00116-0000-00 | I19: Residential / unspecified | J19: Tax lien (Sci Fa sur tax lien) | K19: Individual | L19: Rectenwald, Scott | M19: South Allegheny School District | N19: MAIELLO BRUNGO & MAIELLO | O19: 24808.23 | Q19: 24808.23 | S19: ✔ ✔ ✔ – | T19: VERIFY – Service/3129.2/3129.3 checked, OK not yet checked, no items listed | U19: Bankruptcy history: 1 filing(s) | V19: CHP 13 CN 25-21736 FILED ON 7/1/25 BKD RCVD 6-29-26 | W19: Port Vue Boro | X19: =IFERROR(VLOOKUP(W19,'Transfer Tax'!$A$14:$H$400,8,FALSE),"") | Z19: =IF(OR(Y19="",X19=""),"",Y19*'Transfer Tax'!$B$6*X19) | AE19: 2026-10-25
A20: 104AUG26 | B20: MG-24-000780 | C20: 90 Highland Ave | D20: Mc Kees Rocks | E20: 15136 | F20: Stowe | G20: 73-S-277 | H20: 0073-S-00277-0000-00 | I20: Residential / unspecified | J20: Mortgage foreclosure | K20: Entity (LLC/LP/Inc) | L20: Royal Realty by TLM LLC | M20: U.S. Bank Trust Company National Association | N20: McCalla Raymer Leibert Pierce LLC | O20: 10813.64 | Q20: 10813.64 | S20: ✔ ✔ – – | T20: Only Rule 3129.3 outstanding • Rule 3129.3 notice of postponed sale date (for 11/2/26) | V20: NEED 3129.3 FOR 11-2-26 | W20: Stowe Twp | X20: =IFERROR(VLOOKUP(W20,'Transfer Tax'!$A$14:$H$400,8,FALSE),"") | Z20: =IF(OR(Y20="",X20=""),"",Y20*'Transfer Tax'!$B$6*X20) | AE20: 2026-10-25
A21: 55AUG26 | B21: GD-17-009395 | C21: 1800 Montier St | D21: Pittsburgh | E21: 15221 | F21: Wilkinsburg | G21: 232-M-47 | H21: 0232-M-00047-0000-00 | I21: Residential / unspecified | J21: Tax lien (Sci Fa sur tax lien) | K21: Individual | L21: Cheatham, Nichole | M21: Wilkinsburg Borough | N21: MAIELLO BRUNGO & MAIELLO | O21: 163825.86 | Q21: 163825.86 | S21: ✔ ✔ – – | T21: Only Rule 3129.3 outstanding • Rule 3129.3 notice of postponed sale date (for 11/2/26) | V21: NEED 3129.3 FOR 11-2-26 | W21: Wilkinsburg Boro | X21: =IFERROR(VLOOKUP(W21,'Transfer Tax'!$A$14:$H$400,8,FALSE),"") | Z21: =IF(OR(Y21="",X21=""),"",Y21*'Transfer Tax'!$B$6*X21) | AE21: 2026-10-25

Sheet Transfer Tax
A1: Realty transfer tax — every Allegheny County municipality
A2: Local rates: Allegheny County Dept. of Real Estate 'Local Realty Transfer Tax Rates' page (cross-checked against ALT Title's deviation list as of 7/1/2025 — all 17 non-standard entries match). Names lightly normalized (e.g., 'Mt.'→'Mount').
A4: INPUTS
A5: State realty transfer tax rate | B5: 0.01 | C5: PA Dept. of Revenue — state RTT is 1%.
A6: Allegheny CLR factor | B6: 2.03 | C6: Source: PA Dept. of Revenue CLR factor list for documents accepted 7/1/2026–6/30/2027 (Allegheny = 2.03). The County's own RTT page still shows the older 1.99.
A7: Example assessed value (try your own) | B7: 40000 | C7: Look up a parcel's assessed value on the County Real Estate portal using the 'County parcel ID' column.
A9: HOW THE TAX IS FIGURED ON A SHERIFF DEED
A10: PA Revenue regulation 61 Pa. Code § 91.135: for transfers by execution, mortgage foreclosure, judicial sale or tax sale, the tax base is COMPUTED VALUE = assessed value × CLR factor — not your winning bid. A cheap bid can still carry a real tax bill.
A11: Example computed value | B11: =B7*B6
A13: Municipality | B13: Municipal rate | C13: School district | D13: School rate | E13: Local total | F13: State rate | G13: Note | H13: Total rate | I13: Tax per $10k assessed | J13: On OK to Sell | K13: On Almost Ready
A14: Aleppo Twp | B14: 0.005 | C14: Quaker Valley School District | D14: 0.005 | E14: =B14+D14 | F14: =$B$5 | H14: =E14+F14 | I14: =10000*$B$6*H14 | J14: =COUNTIF('OK to Sell'!$W:$W,A14) | K14: =COUNTIF('Almost Ready'!$W:$W,A14)
A15: Aspinwall Boro | B15: 0.005 | C15: Fox Chapel Area School District | D15: 0.005 | E15: =B15+D15 | F15: =$B$5 | H15: =E15+F15 | I15: =10000*$B$6*H15 | J15: =COUNTIF('OK to Sell'!$W:$W,A15) | K15: =COUNTIF('Almost Ready'!$W:$W,A15)
A16: Avalon Boro | B16: 0.005 | C16: Northgate School District | D16: 0.005 | E16: =B16+D16 | F16: =$B$5 | H16: =E16+F16 | I16: =10000*$B$6*H16 | J16: =COUNTIF('OK to Sell'!$W:$W,A16) | K16: =COUNTIF('Almost Ready'!$W:$W,A16)
A17: Baldwin Boro | B17: 0.005 | C17: Baldwin-Whitehall School District | D17: 0.005 | E17: =B17+D17 | F17: =$B$5 | H17: =E17+F17 | I17: =10000*$B$6*H17 | J17: =COUNTIF('OK to Sell'!$W:$W,A17) | K17: =COUNTIF('Almost Ready'!$W:$W,A17)
A18: Baldwin Twp | B18: 0.005 | C18: Baldwin-Whitehall School District | D18: 0.005 | E18: =B18+D18 | F18: =$B$5 | H18: =E18+F18 | I18: =10000*$B$6*H18 | J18: =COUNTIF('OK to Sell'!$W:$W,A18) | K18: =COUNTIF('Almost Ready'!$W:$W,A18)
A19: Bellevue Boro | B19: 0.01 | C19: Northgate School District | D19: 0.005 | E19: =B19+D19 | F19: =$B$5 | H19: =E19+F19 | I19: =10000*$B$6*H19 | J19: =COUNTIF('OK to Sell'!$W:$W,A19) | K19: =COUNTIF('Almost Ready'!$W:$W,A19)
A20: Bell Acres Boro | B20: 0.005 | C20: Quaker Valley School District | D20: 0.005 | E20: =B20+D20 | F20: =$B$5 | H20: =E20+F20 | I20: =10000*$B$6*H20 | J20: =COUNTIF('OK to Sell'!$W:$W,A20) | K20: =COUNTIF('Almost Ready'!$W:$W,A20)
A21: Ben Avon Boro | B21: 0.005 | C21: Avonworth School District | D21: 0.005 | E21: =B21+D21 | F21: =$B$5 | H21: =E21+F21 | I21: =10000*$B$6*H21 | J21: =COUNTIF('OK to Sell'!$W:$W,A21) | K21: =COUNTIF('Almost Ready'!$W:$W,A21)
A22: Ben Avon Heights Boro | B22: 0.005 | C22: Avonworth School District | D22: 0.005 | E22: =B22+D22 | F22: =$B$5 | H22: =E22+F22 | I22: =10000*$B$6*H22 | J22: =COUNTIF('OK to Sell'!$W:$W,A22) | K22: =COUNTIF('Almost Ready'!$W:$W,A22)
A23: Bethel Park Municipality | B23: 0.01 | C23: Bethel Park School District | D23: 0.005 | E23: =B23+D23 | F23: =$B$5 | H23: =E23+F23 | I23: =10000*$B$6*H23 | J23: =COUNTIF('OK to Sell'!$W:$W,A23) | K23: =COUNTIF('Almost Ready'!$W:$W,A23)
A24: Blawnox Boro | B24: 0.005 | C24: Fox Chapel Area School District | D24: 0.005 | E24: =B24+D24 | F24: =$B$5 | H24: =E24+F24 | I24: =10000*$B$6*H24 | J24: =COUNTIF('OK to Sell'!$W:$W,A24) | K24: =COUNTIF('Almost Ready'!$W:$W,A24)
A25: Brackenridge Boro | B25: 0.005 | C25: Highlands School District | D25: 0.005 | E25: =B25+D25 | F25: =$B$5 | H25: =E25+F25 | I25: =10000*$B$6*H25 | J25: =COUNTIF('OK to Sell'!$W:$W,A25) | K25: =COUNTIF('Almost Ready'!$W:$W,A25)
... A87: Mount Lebanon Municipality | B87: 0.01 | C87: Mt. Lebanon School District | D87: 0.005 | E87: =B87+D87 | F87: =$B$5 | H87: =E87+F87 | I87: =10000*$B$6*H87 | J87: =COUNTIF('OK to Sell'!$W:$W,A87) | K87: =COUNTIF('Almost Ready'!$W:$W,A87)
A88: Mount Oliver Boro | B88: 0.01 | C88: Pittsburgh School District | D88: 0.01 | E88: =B88+D88 | F88: =$B$5 | G88: In the Pittsburgh School District (1% school rate). | H88: =E88+F88 | I88: =10000*$B$6*H88 | J88: =COUNTIF('OK to Sell'!$W:$W,A88) | K88: =COUNTIF('Almost Ready'!$W:$W,A88)
A89: Munhall Boro | B89: 0.005 | C89: Steel Valley School District | D89: 0.005 | E89: =B89+D89 | F89: =$B$5 | H89: =E89+F89 | I89: =10000*$B$6*H89 | J89: =COUNTIF('OK to Sell'!$W:$W,A89) | K89: =COUNTIF('Almost Ready'!$W:$W,A89)
A90: Neville Twp | B90: 0.005 | C90: Cornell School District | D90: 0.005 | E90: =B90+D90 | F90: =$B$5 | H90: =E90+F90 | I90: =10000*$B$6*H90 | J90: =COUNTIF('OK to Sell'!$W:$W,A90) | K90: =COUNTIF('Almost Ready'!$W:$W,A90)
A91: North Braddock Boro | B91: 0.005 | C91: Woodland Hills School District | D91: 0.005 | E91: =B91+D91 | F91: =$B$5 | H91: =E91+F91 | I91: =10000*$B$6*H91 | J91: =COUNTIF('OK to Sell'!$W:$W,A91) | K91: =COUNTIF('Almost Ready'!$W:$W,A91)
A92: North Fayette Twp | B92: 0.005 | C92: West Allegheny School District | D92: 0.005 | E92: =B92+D92 | F92: =$B$5 | H92: =E92+F92 | I92: =10000*$B$6*H92 | J92: =COUNTIF('OK to Sell'!$W:$W,A92) | K92: =COUNTIF('Almost Ready'!$W:$W,A92)
A93: North Versailles Twp | B93: 0.005 | C93: East Allegheny School District | D93: 0.005 | E93: =B93+D93 | F93: =$B$5 | H93: =E93+F93 | I93: =10000*$B$6*H93 | J93: =COUNTIF('OK to Sell'!$W:$W,A93) | K93: =COUNTIF('Almost Ready'!$W:$W,A93)
A94: Oakdale Boro | B94: 0.005 | C94: West Allegheny School District | D94: 0.005 | E94: =B94+D94 | F94: =$B$5 | H94: =E94+F94 | I94: =10000*$B$6*H94 | J94: =COUNTIF('OK to Sell'!$W:$W,A94) | K94: =COUNTIF('Almost Ready'!$W:$W,A94)
A95: Oakmont Boro | B95: 0.005 | C95: Riverview School District | D95: 0.005 | E95: =B95+D95 | F95: =$B$5 | H95: =E95+F95 | I95: =10000*$B$6*H95 | J95: =COUNTIF('OK to Sell'!$W:$W,A95) | K95: =COUNTIF('Almost Ready'!$W:$W,A95)
A96: O'Hara Twp | B96: 0.01 | C96: Fox Chapel Area School District | D96: 0.005 | E96: =B96+D96 | F96: =$B$5 | H96: =E96+F96 | I96: =10000*$B$6*H96 | J96: =COUNTIF('OK to Sell'!$W:$W,A96) | K96: =COUNTIF('Almost Ready'!$W:$W,A96)
A97: Ohio Twp | B97: 0.005 | C97: Avonworth School District | D97: 0.005 | E97: =B97+D97 | F97: =$B$5 | H97: =E97+F97 | I97: =10000*$B$6*H97 | J97: =COUNTIF('OK to Sell'!$W:$W,A97) | K97: =COUNTIF('Almost Ready'!$W:$W,A97)
A98: Pennsbury Village Boro | B98: 0.005 | C98: Montour School District | D98: 0.005 | E98: =B98+D98 | F98: =$B$5 | H98: =E98+F98 | I98: =10000*$B$6*H98 | J98: =COUNTIF('OK to Sell'!$W:$W,A98) | K98: =COUNTIF('Almost Ready'!$W:$W,A98)
A99: Penn Hills Municipality | B99: 0.015 | C99: Penn Hills School District | D99: 0.005 | E99: =B99+D99 | F99: =$B$5 | H99: =E99+F99 | I99: =10000*$B$6*H99 | J99: =COUNTIF('OK to Sell'!$W:$W,A99) | K99: =COUNTIF('Almost Ready'!$W:$W,A99)
A100: Pine Twp | B100: 0.01 | C100: Pine-Richland School District | D100: 0.005 | E100: =B100+D100 | F100: =$B$5 | H100: =E100+F100 | I100: =10000*$B$6*H100 | J100: =COUNTIF('OK to Sell'!$W:$W,A100) | K100: =COUNTIF('Almost Ready'!$W:$W,A100)
A101: Pitcairn Boro | B101: 0.005 | C101: Gateway School District | D101: 0.005 | E101: =B101+D101 | F101: =$B$5 | H101: =E101+F101 | I101: =10000*$B$6*H101 | J101: =COUNTIF('OK to Sell'!$W:$W,A101) | K101: =COUNTIF('Almost Ready'!$W:$W,A101)
A102: Pittsburgh City (Baldwin-Whitehall SD portion) | B102: 0.03 | C102: Baldwin-Whitehall School District | D102: 0.005 | E102: =B102+D102 | F102: =$B$5 | G102: Small part of the City inside Baldwin-Whitehall SD (e.g., parts of the 32nd Ward). Sheet defaults City parcels to 5% — confirm. | H102: =E102+F102 | I102: =10000*$B$6*H102 | J102: =COUNTIF('OK to Sell'!$W:$W,A102) | K102: =COUNTIF('Almost Ready'!$W:$W,A102)
A103: Pittsburgh City (Pittsburgh SD) | B103: 0.03 | C103: Pittsburgh School District | D103: 0.01 | E103: =B103+D103 | F103: =$B$5 | H103: =E103+F103 | I103: =10000*$B$6*H103 | J103: =COUNTIF('OK to Sell'!$W:$W,A103) | K103: =COUNTIF('Almost Ready'!$W:$W,A103)
A104: Pleasant Hills Boro | B104: 0.005 | C104: West Jefferson Hills School District | D104: 0.005 | E104: =B104+D104 | F104: =$B$5 | H104: =E104+F104 | I104: =10000*$B$6*H104 | J104: =COUNTIF('OK to Sell'!$W:$W,A104) | K104: =COUNTIF('Almost Ready'!$W:$W,A104)
A105: Plum Boro | B105: 0.005 | C105: Plum Borough School District | D105: 0.005 | E105: =B105+D105 | F105: =$B$5 | H105: =E105+F105 | I105: =10000*$B$6*H105 | J105: =COUNTIF('OK to Sell'!$W:$W,A105) | K105: =COUNTIF('Almost Ready'!$W:$W,A105)
A106: Port Vue Boro | B106: 0.005 | C106: South Allegheny School District | D106: 0.005 | E106: =B106+D106 | F106: =$B$5 | H106: =E106+F106 | I106: =10000*$B$6*H106 | J106: =COUNTIF('OK to Sell'!$W:$W,A106) | K106: =COUNTIF('Almost Ready'!$W:$W,A106)
A107: Rankin Boro | B107: 0.005 | C107: Woodland Hills School District | D107: 0.005 | E107: =B107+D107 | F107: =$B$5 | H107: =E107+F107 | I107: =10000*$B$6*H107 | J107: =COUNTIF('OK to Sell'!$W:$W,A107) | K107: =COUNTIF('Almost Ready'!$W:$W,A107)
A108: Reserve Twp | B108: 0.005 | C108: Shaler Area School District | D108: 0.005 | E108: =B108+D108 | F108: =$B$5 | H108: =E108+F108 | I108: =10000*$B$6*H108 | J108: =COUNTIF('OK to Sell'!$W:$W,A108) | K108: =COUNTIF('Almost Ready'!$W:$W,A108)
A109: Richland Twp | B109: 0.005 | C109: Pine-Richland School District | D109: 0.005 | E109: =B109+D109 | F109: =$B$5 | H109: =E109+F109 | I109: =10000*$B$6*H109 | J109: =COUNTIF('OK to Sell'!$W:$W,A109) | K109: =COUNTIF('Almost Ready'!$W:$W,A109)
A110: Robinson Twp | B110: 0.005 | C110: Montour School District | D110: 0.005 | E110: =B110+D110 | F110: =$B$5 | H110: =E110+F110 | I110: =10000*$B$6*H110 | J110: =COUNTIF('OK to Sell'!$W:$W,A110) | K110: =COUNTIF('Almost Ready'!$W:$W,A110)
A111: Ross Twp | B111: 0.005 | C111: North Hills School District | D111: 0.005 | E111: =B111+D111 | F111: =$B$5 | H111: =E111+F111 | I111: =10000*$B$6*H111 | J111: =COUNTIF('OK to Sell'!$W:$W,A111) | K111: =COUNTIF('Almost Ready'!$W:$W,A111)
A112: Rosslyn Farms Boro | B112: 0.005 | C112: Carlynton School District | D112: 0.005 | E112: =B112+D112 | F112: =$B$5 | H112: =E112+F112 | I112: =10000*$B$6*H112 | J112: =COUNTIF('OK to Sell'!$W:$W,A112) | K112: =COUNTIF('Almost Ready'!$W:$W,A112)
A113: Scott Twp | B113: 0.005 | C113: Chartiers Valley School District | D113: 0.005 | E113: =B113+D113 | F113: =$B$5 | H113: =E113+F113 | I113: =10000*$B$6*H113 | J113: =COUNTIF('OK to Sell'!$W:$W,A113) | K113: =COUNTIF('Almost Ready'!$W:$W,A113)
A114: Sewickley Boro | B114: 0.005 | C114: Quaker Valley School District | D114: 0.005 | E114: =B114+D114 | F114: =$B$5 | H114: =E114+F114 | I114: =10000*$B$6*H114 | J114: =COUNTIF('OK to Sell'!$W:$W,A114) | K114: =COUNTIF('Almost Ready'!$W:$W,A114)
... A127: Thornburg Boro | B127: 0.005 | C127: Montour School District | D127: 0.005 | E127: =B127+D127 | F127: =$B$5 | H127: =E127+F127 | I127: =10000*$B$6*H127 | J127: =COUNTIF('OK to Sell'!$W:$W,A127) | K127: =COUNTIF('Almost Ready'!$W:$W,A127)
A128: Trafford Boro | B128: 0.01 | C128: No school realty transfer tax | D128: 0 | E128: =B128+D128 | F128: =$B$5 | G128: Mostly in Westmoreland County; no school RTT listed. | H128: =E128+F128 | I128: =10000*$B$6*H128 | J128: =COUNTIF('OK to Sell'!$W:$W,A128) | K128: =COUNTIF('Almost Ready'!$W:$W,A128)
A129: Turtle Creek Boro | B129: 0.005 | C129: Woodland Hills School District | D129: 0.005 | E129: =B129+D129 | F129: =$B$5 | H129: =E129+F129 | I129: =10000*$B$6*H129 | J129: =COUNTIF('OK to Sell'!$W:$W,A129) | K129: =COUNTIF('Almost Ready'!$W:$W,A129)
A130: Upper St. Clair Twp | B130: 0.01 | C130: Upper St. Clair School District | D130: 0.005 | E130: =B130+D130 | F130: =$B$5 | H130: =E130+F130 | I130: =10000*$B$6*H130 | J130: =COUNTIF('OK to Sell'!$W:$W,A130) | K130: =COUNTIF('Almost Ready'!$W:$W,A130)
A131: Versailles Boro | B131: 0.005 | C131: McKeesport Area School District | D131: 0.005 | E131: =B131+D131 | F131: =$B$5 | H131: =E131+F131 | I131: =10000*$B$6*H131 | J131: =COUNTIF('OK to Sell'!$W:$W,A131) | K131: =COUNTIF('Almost Ready'!$W:$W,A131)
A132: Verona Boro | B132: 0.005 | C132: Riverview School District | D132: 0.005 | E132: =B132+D132 | F132: =$B$5 | H132: =E132+F132 | I132: =10000*$B$6*H132 | J132: =COUNTIF('OK to Sell'!$W:$W,A132) | K132: =COUNTIF('Almost Ready'!$W:$W,A132)
A133: Wall Boro | B133: 0.005 | C133: East Allegheny School District | D133: 0.005 | E133: =B133+D133 | F133: =$B$5 | H133: =E133+F133 | I133: =10000*$B$6*H133 | J133: =COUNTIF('OK to Sell'!$W:$W,A133) | K133: =COUNTIF('Almost Ready'!$W:$W,A133)
A134: West Deer Twp | B134: 0.01 | C134: Deer Lakes School District | D134: 0.005 | E134: =B134+D134 | F134: =$B$5 | H134: =E134+F134 | I134: =10000*$B$6*H134 | J134: =COUNTIF('OK to Sell'!$W:$W,A134) | K134: =COUNTIF('Almost Ready'!$W:$W,A134)
A135: West Elizabeth Boro | B135: 0.005 | C135: West Jefferson Hills School District | D135: 0.005 | E135: =B135+D135 | F135: =$B$5 | H135: =E135+F135 | I135: =10000*$B$6*H135 | J135: =COUNTIF('OK to Sell'!$W:$W,A135) | K135: =COUNTIF('Almost Ready'!$W:$W,A135)
A136: West Homestead Boro | B136: 0.005 | C136: Steel Valley School District | D136: 0.005 | E136: =B136+D136 | F136: =$B$5 | H136: =E136+F136 | I136: =10000*$B$6*H136 | J136: =COUNTIF('OK to Sell'!$W:$W,A136) | K136: =COUNTIF('Almost Ready'!$W:$W,A136)
A137: West Mifflin Boro | B137: 0.005 | C137: West Mifflin Area School District | D137: 0.005 | E137: =B137+D137 | F137: =$B$5 | H137: =E137+F137 | I137: =10000*$B$6*H137 | J137: =COUNTIF('OK to Sell'!$W:$W,A137) | K137: =COUNTIF('Almost Ready'!$W:$W,A137)
A138: West View Boro | B138: 0.005 | C138: North Hills School District | D138: 0.005 | E138: =B138+D138 | F138: =$B$5 | H138: =E138+F138 | I138: =10000*$B$6*H138 | J138: =COUNTIF('OK to Sell'!$W:$W,A138) | K138: =COUNTIF('Almost Ready'!$W:$W,A138)
A139: Whitaker Boro | B139: 0.005 | C139: West Mifflin Area School District | D139: 0.005 | E139: =B139+D139 | F139: =$B$5 | H139: =E139+F139 | I139: =10000*$B$6*H139 | J139: =COUNTIF('OK to Sell'!$W:$W,A139) | K139: =COUNTIF('Almost Ready'!$W:$W,A139)
A140: Whitehall Boro | B140: 0.01 | C140: Baldwin-Whitehall School District | D140: 0.005 | E140: =B140+D140 | F140: =$B$5 | H140: =E140+F140 | I140: =10000*$B$6*H140 | J140: =COUNTIF('OK to Sell'!$W:$W,A140) | K140: =COUNTIF('Almost Ready'!$W:$W,A140)
... A144: Wilmerding Boro | B144: 0.005 | C144: East Allegheny School District | D144: 0.005 | E144: =B144+D144 | F144: =$B$5 | H144: =E144+F144 | I144: =10000*$B$6*H144 | J144: =COUNTIF('OK to Sell'!$W:$W,A144) | K144: =COUNTIF('Almost Ready'!$W:$W,A144)

Sheet Glossary
A1: How to read the Sheriff notes, and what each sale type means for a bidder
A2: Educational, Pennsylvania / Allegheny County context — not legal advice. Title outcomes at a sheriff sale depend on lien priority and notice; have a PA title company or real-estate attorney confirm before bidding on any specific parcel.
A4: SALE TYPES
A5: Tax lien (Sci Fa sur tax lien) | B5: A school district, municipality or the County is enforcing unpaid real-estate tax claims through a writ of scire facias. The Cost & Tax bid is the opening bid covering the claim plus costs. Which other liens are wiped out depends on priority and proper notice — do not assume "free and clear" unless there is a free & clear court order.
A6: Free & clear court order (F/C O/C) + min bid | B6: The court has authorized sale free and clear of liens at the stated minimum bid, which can be far below the listed Cost & Tax bid. Read the actual order on the docket to confirm scope.
A7: Mortgage foreclosure | B7: A lender is selling under its foreclosure judgment. The Cost & Tax bid is only costs and taxes; the lender can credit-bid up to its judgment (see "Reassessed damages"), so outside bidders usually need to beat the lender's announced bid. Liens senior to the mortgage can survive.
A8: HOA / condo assessment judgment | B8: An association is executing on a money judgment for unpaid assessments (AR- case numbers). Because this is usually a junior lien, a first mortgage on the unit may survive the sale — potentially a large hidden liability. Get a title search before bidding.
A9: Other judgment execution | B9: A creditor executing on a general money judgment (e.g., business lenders). Senior liens and mortgages typically survive.
A10: Municipal lien | B10: A municipal claim (non-tax, e.g., sewer/water/demolition) enforced by sheriff sale.
A12: LISTED STATUSES
A13: Active | B13: Scheduled to go to the upcoming sale — but the Sheriff will only sell if the paperwork is complete (see the four boxes and notes).
A14: Postponed / Postponed (Waived) | B14: Moved to the date shown. 12/31/2099 = indefinite (Save Your Home program). The meaning of "(Waived)" is not stated on the list.
A15: Stayed | B15: Sale halted (bankruptcy, payment plan, court order). "Amount realized" = money collected on the stay.
A16: Money Made | B16: The claim was paid/satisfied; the property won't be sold.
A18: THE FOUR BOXES
A19: Svs | B19: Service of the writ/notice on the defendant has been made.
A20: 3129.2 | B20: Pa.R.C.P. 3129.2 — notice of sale (handbills, written notice to owners/lienholders, publication). Written notice must be served at least 30 days before the sale; the Sheriff rejects late ones.
A21: 3129.3 | B21: Pa.R.C.P. 3129.3 — postponement of sale / new notice. Needed when a sale was postponed to this date. Often filed in the last day or two before the sale, which is why cases missing only this item are listed on Almost Ready.
A22: OK | B22: Sheriff has everything needed and has cleared the property to sell on this date.
A24: ABBREVIATIONS IN NOTES
A25: O/C | B25: Order of court. "NEED O/C FOR [dates]" = a court order approving the chain of postponements through those sale dates; the Sheriff rejects orders that skip a date or list them out of sequence.
A26: BK / BKD / BKDR | B26: Bankruptcy / bankruptcy dismissal or relief-from-stay docs. A pending bankruptcy automatically stays the sale until the Sheriff receives the dismissal or relief order.
A27: NSM ON DEF(S) | B27: No service made on the defendant(s) — proof of service still needed.
A28: PP | B28: Postponement.
A29: NOS | B29: Notice of sale.
A30: SYH | B30: Save Your Home — Allegheny County foreclosure-diversion/conciliation program.
A31: Replenishment invoice | B31: Plaintiff owes the Sheriff an additional cost deposit; the case cannot go to sale until paid.
A32: Reassess damages | B32: Court order updating the judgment amount (the most recent figure is shown in the sheet).
A33: Forfeited | B33: A previous winning bidder failed to pay the balance and lost the deposit; the property is being re-offered.
A34: Handbill / short description | B34: Sale advertising materials. If late or incorrect, the Sheriff requires a postponement.
A35: C+T | B35: Cost & Tax (the opening bid).
A37: LIEN FLAGS
A38: Federal tax lien / IRS lien | B38: Whether a federal tax lien is discharged depends on whether the United States was properly joined. When it is joined, the IRS generally keeps a right to redeem (buy back) the property after the sale (28 U.S.C. § 2410(c); IRM 5.12.5).
A39: HOA 6-month statutory amount | B39: PA planned-community and condo statutes give associations limited priority (about six months of assessments) over a first mortgage; the rest of the HOA debt is junior.
A40: PA DHS lien | B40: Commonwealth Dept. of Human Services lien (e.g., estate recovery). Check whether it is divested.
A41: Land bank decree | B41: Land bank involvement noted on the case — confirm whether a land bank intends to bid or has priority before investing time.
A43: METHOD
A44: How readiness was derived | B44: OK to Sell = Active, residential, Sheriff OK box checked, and no outstanding items in the notes other than Rule 3129.3. Almost Ready = Active, residential, Service and 3129.2 boxes checked, and the only outstanding item is Rule 3129.3 — plus "VERIFY" cases where the OK box and the notes disagree. Everything else (postponed, stayed, paid, bankruptcy, court orders or service still needed, commercial / industrial / vacant land) is left off the sheet.
A45: Source | B45: Allegheny County Sheriff — Sale Listings PDF from sheriffalleghenycounty.com/sheriffs-sales/. The Sheriff states the binding bid list is finalized the morning of the sale; the version and print time used for the latest update are on the Overview tab.
A47: TRANSFER TAX
A48: Realty transfer tax on a sheriff deed | B48: 1% state + 1%–4% local depending on municipality and school district (2% in most suburbs, 5% in the City of Pittsburgh). On sheriff, foreclosure and tax-sale deeds the base is computed value (assessed value × CLR factor, 2.03 for 7/1/2026–6/30/2027), not the bid (61 Pa. Code § 91.135). With no seller to split it, the buyer bears it. See the Transfer Tax sheet.

Sheet _Data
A1: sale_id | B1: case_no | C1: address | D1: municipality | E1: status | F1: bucket | G1: bucket_reason | H1: opening_bid | I1: flags
A2: 40JUL19 | B2: GD-18-001488 | C2: 227 Marland St | D2: Pittsburgh | E2: Postponed to 5/3/2027 | F2: excluded | G2: Postponed to 5/3/2027 | H2: 45742.95 | I2: Free & clear order at "upset price" Prior winning bidder forfeited (property re-offered) Bankruptcy history: 7 filing(s)
A3: 55DEC19 | B3: GD-16-010596 | C3: 6 Michigan Rd | D3: Penn Hills | E3: Postponed to 1/4/2027 | F3: excluded | G3: Postponed to 1/4/2027 | H3: 36514.43 | I3: Bankruptcy history: 3 filing(s)
A4: 9NOV21 | B4: GD-20-001165 | C4: 109 E 18th Ave | D4: Homestead | E4: Active | F4: excluded | G4: Docs outstanding: Court order (O/C) approving postponements covering 9 sale date(s): 11/4/24, 2/3/25, 3/3/25, 7/7/25, 9/2/25, 12/1/25, 3/2/26, 7/6/26, 8/3/26 | H4: 54086.54
A5: 49JAN22 | B5: GD-15-007385 | C5: 203 E 20th Ave | D5: Munhall | E5: Active | F5: excluded | G5: Docs outstanding: Replenishment invoice must be paid; Court order (O/C) approving postponements covering 12 sale date(s): 12/2/24, 4/7/25, 5/5/25, 7/7/25, 10/6/25, 11/3/25, 2/2/26, 5/4/26, 6/1/26, 8/3/26, 9/8/26, 11/2/26; Rule 3129.3 notice of postponed sale date (for 11/2/26) | H5: 56115.05 | I5: Defense attorney has entered an appearance
A6: 51JAN22 | B6: GD-19-016470 | C6: 4101 Superior St | D6: Munhall | E6: Postponed to 1/4/2027 | F6: excluded | G6: Postponed to 1/4/2027 | H6: 62369.21
A7: 89JAN22 | B7: GD-16-015649 | C7: 3706 Home St | D7: West Mifflin | E7: Postponed to 1/4/2027 | F7: excluded | G7: Postponed to 1/4/2027 | H7: 51324.55
A8: 89JUN22 | B8: MG-20-000017 | C8: 327 Greenway Dr | D8: Penn Hills | E8: Active | F8: excluded | G8: Bankruptcy dismissal / relief-from-stay docs | H8: 3132.68 | I8: Bankruptcy history: 2 filing(s)
A9: 31AUG22 | B9: GD-19-008607 | C9: 109 Lavern St | D9: Penn Hills | E9: Postponed to 12/7/2026 | F9: excluded | G9: Postponed to 12/7/2026 | H9: 70636.94
A10: 5NOV22 | B10: GD-20-008893 | C10: 428 Dennison Dr | D10: West Mifflin | E10: Active | F10: excluded | G10: Docs outstanding: Court order (O/C) approving postponements covering 15 sale date(s): 6/5/23, 3/3/25, 5/5/25, 6/2/25, 7/7/25, 8/4/25, 9/2/25, 11/3/25, 1/5/26, 4/6/26, 5/4/26, 6/1/26, 8/3/26, 9/8/26, 11/2/26 | H10: 37741.72
A11: 43JAN23 | B11: GD-22-005972 | C11: 2146 Sampson St | D11: Penn Hills | E11: Active | F11: excluded | G11: Bankruptcy dismissal / relief-from-stay docs | H11: 31122.59 | I11: Bankruptcy history: 2 filing(s)
A12: 35JUL23 | B12: GD-22-013060 | C12: 26-28 Oak Street | D12: West Deer | E12: Active | F12: excluded | G12: Bankruptcy dismissal / relief-from-stay docs | H12: 44823.2 | I12: Bankruptcy history: 1 filing(s)
A13: 28NOV23 | B13: GD-22-004165 | C13: 2602 Milburn Street | D13: McKeesport | E13: Active | F13: excluded | G13: Docs outstanding: Court order (O/C) approving postponements covering 11 sale date(s): 5/6/24, 7/1/24, 11/4/24, 3/3/25, 6/2/25, 9/2/25, 11/3/25, 2/2/26, 5/4/26, 8/3/26, 11/2/26; Rule 3129.3 notice of postponed sale date (for 11/2/26) | H13: 22299.84
A14: 36APR24 | B14: GD-22-000743 | C14: 741 Michigan Avenue | D14: Glassport | E14: Postponed to 3/1/2027 | F14: excluded | G14: Postponed to 3/1/2027 | H14: 33206.67 | I14: Bankruptcy history: 2 filing(s)
A15: 49AUG24 | B15: GD-23-008764 | C15: Union Ave | D15: McKeesport | E15: Active | F15: excluded | G15: Non-residential (Vacant Land) | H15: 21794.65 | I15: Free & clear order at "upset price"
A16: 2NOV24 | B16: GD-23-014272 | C16: 61 Bellanca Avenue | D16: Brentwood | E16: Active | F16: ok | G16: Sheriff OK box checked | H16: 14000 | I16: Free & clear court order, min bid $14,000.00 Bankruptcy history: 2 filing(s)
A17: 37DEC24 | B17: GD-23-003880 | C17: 1319 S Canal Street ; 1324 Middle St | D17: Sharpsburg | E17: Active | F17: excluded | G17: Docs outstanding: Replenishment invoice must be paid; Rule 3129.3 notice of postponed sale date (for 11/2/26); Court order (O/C) approving postponements covering 7 sale date(s): 11/3/25, 1/5/26, 3/2/26, 5/4/26, 7/6/26, 9/8/26, 11/2/26 | H17: 43057.51
A18: 39DEC24 | B18: GD-24-004172 | C18: 858 Punta Gorda Ave | D18: East McKeesport | E18: Active | F18: excluded | G18: Docs outstanding: Rule 3129.3 notice of postponed sale date (for 11/2/26); Court order (O/C) approving postponements covering 2 sale date(s): 10/5/26, 11/2/26 | H18: 25961.14
A19: 57DEC24 | B19: GD-24-001709 | C19: 117 Spring Grove Road | D19: Penn Hills | E19: Active | F19: excluded | G19: Docs outstanding: Court order (O/C) approving postponements covering 1 sale date(s): 11/2/26 | H19: 34308.17
A20: 86DEC24 | B20: GD-17-014538 | C20: 1651 Ellsworth Ave | D20: Heidelberg | E20: Stayed | F20: excluded | G20: Stayed | H20: 49628.61 | I20: Bankruptcy history: 1 filing(s)
A21: 101DEC24 | B21: GD-23-009031 | C21: 114 S 6th St | D21: Duquesne | E21: Active | F21: excluded | G21: Docs outstanding: Replenishment invoice must be paid; Rule 3129.3 notice of postponed sale date (for 11/2/26); Court order (O/C) approving postponements covering 7 sale date(s): 6/2/25, 9/2/25, 12/1/25, 2/2/26, 5/4/26, 8/3/26, 11/2/26 | H21: 37078.04
A22: 21JAN25 | B22: GD-23-010343 | C22: 931 Morton Avenue | D22: Port Vue | E22: Postponed to 5/3/2027 | F22: excluded | G22: Postponed to 5/3/2027 | H22: 26939.19
A23: 52JAN25 | B23: GD-24-007223 | C23: 820 Mckee St | D23: Wilkinsburg | E23: Active | F23: excluded | G23: Docs outstanding: Court order (O/C) approving postponements covering 1 sale date(s): 11/2/26 | H23: 39223.38 | I23: Bankruptcy history: 1 filing(s)
A24: 55JAN25 | B24: GD-24-003710 | C24: 523 Delaware Ave ; 509 Monongahela Ave | D24: Glassport | E24: Stayed | F24: excluded | G24: Stayed | H24: 38953.12
A25: 71MAR25 | B25: GD-23-010691 | C25: 7134 Doak St | D25: Penn Hills | E25: Postponed to 5/3/2027 | F25: excluded | G25: Postponed to 5/3/2027 | H25: 22646.85 | I25: Bankruptcy history: 1 filing(s)
A26: 26APR25 | B26: MG-18-001363 | C26: 824 Arbordale Ln | D26: Marshall | E26: Postponed to 1/4/2027 | F26: excluded | G26: Postponed to 1/4/2027 | H26: 21512.1
A27: 114APR25 | B27: GD-24-002249 | C27: 4009 Outlook Dr | D27: West Mifflin | E27: Active | F27: excluded | G27: Docs outstanding: Court order (O/C) approving postponements covering 1 sale date(s): 11/2/26; Rule 3129.3 notice of postponed sale date (for 11/2/26) | H27: 27924.07
A28: 16MAY25 | B28: GD-23-009536 | C28: 6358 Lowell Drive | D28: Penn Hills | E28: Postponed to 1/4/2027 | F28: excluded | G28: Postponed to 1/4/2027 | H28: 44573.67 | I28: Bankruptcy history: 1 filing(s)
A29: 29MAY25 | B29: AR-24-004832 | C29: 401 Beech Street | D29: Richland | E29: Active | F29: excluded | G29: Docs outstanding: Court order (O/C) approving postponements covering 1 sale date(s): 11/2/26; Rule 3129.3 notice of postponed sale date (for 11/2/26) | H29: 2651.15 | I29: Prior winning bidder forfeited (property re-offered) Bankruptcy history: 1 filing(s) HOA/condo judgment sale — a first mortgage may survive the sale
A30: 34MAY25 | B30: GD-22-009214 | C30: 435-437 Freeport Rd | D30: East Deer | E30: Active | F30: excluded | G30: Docs outstanding: Court order (O/C) approving postponements covering 9 sale date(s): 2/2/26, 3/2/26, 4/6/26, 5/4/26, 7/6/26, 8/3/26, 9/8/26, 10/5/26, 11/2/26 | H30: 40986.76
A31: 96MAY25 | B31: GD-22-008777 | C31: 5186 Elmwood Dr | D31: Baldwin Boro | E31: Active | F31: excluded | G31: Docs outstanding: Rule 3129.2 notice of sale / affidavit of service; Court order (O/C) approving postponements covering 1 sale date(s): 4/17/26 | H31: 22816.36
A32: 16JUN25 | B32: GD-24-009484 | C32: 1317 New York Avenue | D32: Port Vue | E32: Active | F32: excluded | G32: Docs outstanding: Court order (O/C) approving postponements covering 1 sale date(s): 8/3/26 | H32: 3833.01
A33: 106JUN25 | B33: GD-22-015400 | C33: 545 Boquet St | D33: Carnegie | E33: Stayed | F33: excluded | G33: Stayed | H33: 33877.59
A34: 119JUN25 | B34: GD-24-011281 | C34: 2812 Wadlow St | D34: Pittsburgh | E34: Active | F34: almost | G34: Only Rule 3129.3 outstanding | H34: 16622.72
A35: 10JUL25 | B35: GD-24-008111 | C35: 819 Hartman Street | D35: McKeesport | E35: Active | F35: excluded | G35: Docs outstanding: Rule 3129.3 notice of postponed sale date (for 11/2/26); Court order (O/C) approving postponements covering 5 sale date(s): 12/1/25, 2/2/26, 5/4/26, 8/3/26, 11/2/26 | H35: 25000.42
A36: 15JUL25 | B36: MG-24-000238 | C36: 649 Greenlee Road | D36: Whitehall | E36: Active | F36: excluded | G36: Docs outstanding: Rule 3129.3 notice of postponed sale date (for 11/2/26); Court order (O/C) approving postponements covering 1 sale date(s): 9/8/26 | H36: 6160.45
A37: 18JUL25 | B37: MG-24-000230 | C37: 2418 Charles St | D37: Munhall | E37: Active | F37: excluded | G37: Bankruptcy dismissal / relief-from-stay docs | H37: 9504.04 | I37: Bankruptcy history: 1 filing(s)
A38: 42JUL25 | B38: GD-21-008104 | C38: 315 W 13th Ave | D38: Homestead | E38: Postponed to 12/7/2026 | F38: excluded | G38: Postponed to 12/7/2026 | H38: 42911.59
A39: 72JUL25 | B39: GD-23-012485 | C39: 528 Dewey Ave | D39: Bridgeville | E39: Active | F39: excluded | G39: Non-residential (Commercial) | H39: 502839.51
A40: 85JUL25 | B40: GD-24-010996 | C40: 1204 Washington Boulevard Rear | D40: Port Vue | E40: Active | F40: almost | G40: VERIFY – Service/3129.2/3129.3 checked, OK not yet checked, no items listed | H40: 24808.23 | I40: Bankruptcy history: 1 filing(s)
A41: 1AUG25 | B41: GD-24-006939 | C41: 5631 Baum Boulevard ; 5607 Baum Blvd ; 420 Roup Ave | D41: Pittsburgh | E41: Active | F41: excluded | G41: Non-residential (Commercial) | H41: 152020.26
A42: 50AUG25 | B42: MG-24-000428 | C42: 2098 North Rd ; 2098 North Road | D42: North Fayette | E42: Active | F42: excluded | G42: Handbill / short-description defect – Sheriff says sale must be postponed | H42: 4668.86
A43: 55AUG25 | B43: MG-25-000026 | C43: 7315 Beacon Hill Drive | D43: Wilkinsburg | E43: Active | F43: excluded | G43: Handbill / short-description defect – Sheriff says sale must be postponed | H43: 2983.36
A44: 89SEP25 | B44: GD-24-004499 | C44: 1976 Mcnary Boulevard | D44: Wilkinsburg | E44: Postponed to 12/7/2026 | F44: excluded | G44: Postponed to 12/7/2026 | H44: 15407.98
A45: 123SEP25 | B45: GD-25-003677 | C45: 834 Vallevista Avenue | D45: Mount Lebanon | E45: Active | F45: excluded | G45: Bankruptcy dismissal / relief-from-stay docs | H45: 7424.22 | I45: Bankruptcy history: 1 filing(s)
A46: 3OCT25 | B46: AR-24-006314 | C46: 229 Thornberry Drive | D46: Ross | E46: Active | F46: excluded | G46: Docs outstanding: Court order (O/C) approving postponements covering 1 sale date(s): 11/2/26 | H46: 13130.58 | I46: Prior winning bidder forfeited (property re-offered) Bankruptcy history: 1 filing(s) HOA/condo judgment sale — a first mortgage may survive the sale
A47: 7OCT25 | B47: GD-22-012869 | C47: 417 Allegheny Avenue | D47: Plum | E47: Active | F47: excluded | G47: Docs outstanding: Rule 3129.3 notice of postponed sale date (for 11/2/26); Court order (O/C) approving postponements covering 4 sale date(s): 4/6/26, 7/6/26, 8/3/26, 11/2/26 | H47: 39205.94
A48: 16OCT25 | B48: GD-25-004673 | C48: 4115 Ben Miller Road | D48: Richland | E48: Stayed | F48: excluded | G48: Stayed | H48: 4611.6 | I48: OK-to-sell note dated 9/8/26, not this sale – verify
A49: 17OCT25 | B49: MG-23-000226 | C49: 1160 Mckenna Ave | D49: Pittsburgh | E49: Postponed to 1/4/2027 | F49: excluded | G49: Postponed to 1/4/2027 | H49: 7990.12
A50: 47OCT25 | B50: GD-22-003299 | C50: 111 Glenwood Drive | D50: Elizabeth Twp | E50: Active | F50: excluded | G50: Docs outstanding: Court order (O/C) approving postponements covering 3 sale date(s): 3/2/26, 6/1/26, 7/6/26 | H50: 30843.02 | I50: Bankruptcy history: 1 filing(s)
A51: 61OCT25 | B51: GD-23-014497 | C51: 7326 Church Street | D51: Swissvale | E51: Active | F51: excluded | G51: Docs outstanding: Court order (O/C) approving postponements covering 2 sale date(s): 5/4/26, 11/2/26 | H51: 19587.22
A52: 76OCT25 | B52: GD-24-010288 | C52: 2529 Orlando Pl | D52: Penn Hills | E52: Active | F52: excluded | G52: Docs outstanding: Court order (O/C) approving postponements covering 1 sale date(s): 11/2/26 | H52: 75108.76
A53: 101OCT25 | B53: MG-25-000232 | C53: 84 Houck Street | D53: North Versailles | E53: Active | F53: excluded | G53: Bankruptcy dismissal / relief-from-stay docs | H53: 3076.39 | I53: Bankruptcy history: 2 filing(s)
A54: 12NOV25 | B54: MG-23-000977 | C54: 2546 Haymaker Rd , PA 15146 | D54: Monroeville | E54: Postponed to 2/1/2027 | F54: excluded | G54: Postponed to 2/1/2027 | H54: 3647.99
A55: 21NOV25 | B55: GD-20-005748 | C55: 1320 Louise St | D55: Munhall | E55: Active | F55: excluded | G55: Docs outstanding: Court order (O/C) approving postponements covering 4 sale date(s): 6/1/26, 8/3/26, 9/8/26, 11/2/26 | H55: 28798.04
A56: 45NOV25 | B56: MG-19-000272 | C56: 700 Penn St | D56: Sharpsburg | E56: Active | F56: excluded | G56: Docs outstanding: Court order (O/C) approving postponements covering 3 sale date(s): 8/3/26, 10/5/26, 11/2/26 | H56: 2858.3
A57: 54NOV25 | B57: GD-23-011927 | C57: 220 Old Lebanon Church Rd | D57: Pleasant Hills | E57: Active | F57: ok | G57: Sheriff OK box checked | H57: 25000 | I57: Free & clear court order, min bid $25,000.00 (earlier orders: $100,000.00) Prior winning bidder forfeited (property re-offered) Opening bid recalculated – new C+T bid $152,696.57
A58: 70NOV25 | B58: GD-24-006729 | C58: 1079 8th Avenue | D58: Brackenridge | E58: Active | F58: excluded | G58: Docs outstanding: Court order (O/C) approving postponements covering 2 sale date(s): 8/3/26, 11/2/26 | H58: 25543.5
A59: 90NOV25 | B59: GD-23-010754 | C59: 804 Washington Street | D59: Harrison | E59: Postponed to 5/3/2027 | F59: excluded | G59: Postponed to 5/3/2027 | H59: 24306.47 | I59: Bankruptcy history: 1 filing(s)
A60: 101NOV25 | B60: GD-17-005317 | C60: 3602 Cambria St | D60: Munhall | E60: Active | F60: excluded | G60: Docs outstanding: Court order (O/C) approving postponements covering 2 sale date(s): 9/8/26, 11/2/26 | H60: 14822.61
A61: 104NOV25 | B61: MG-23-001072 | C61: 432 Dennison Drive | D61: West Mifflin | E61: Postponed to 3/1/2027 | F61: excluded | G61: Postponed to 3/1/2027 | H61: 2609.93
A62: 21DEC25 | B62: GD-24-011080 | C62: 3700 Vistaview St | D62: West Mifflin | E62: Active | F62: excluded | G62: Docs outstanding: Court order (O/C) approving postponements covering 2 sale date(s): 5/4/26, 11/2/26 | H62: 52851.66
A63: 22DEC25 | B63: GD-24-000740 | C63: 116 Regina St | D63: Whitaker | E63: Active | F63: excluded | G63: Docs outstanding: Court order (O/C) approving postponements covering 5 sale date(s): 2/2/26, 4/6/26, 8/3/26, 9/8/26, 11/2/26 | H63: 23138.32
A64: 46DEC25 | B64: GD-23-010643 | C64: 2801 Penn Ave | D64: Pittsburgh | E64: Active | F64: excluded | G64: Non-residential (Commercial) | H64: 37308.66 | I64: Defense attorney has entered an appearance
A65: 57DEC25 | B65: GD-18-016940 | C65: 124 Bell Street | D65: Elizabeth Twp | E65: Active | F65: excluded | G65: Docs outstanding: Court order (O/C) approving postponements covering 2 sale date(s): 5/4/26, 11/2/26 | H65: 28147.55
A66: 85DEC25 | B66: GD-25-000444 | C66: 716 Kentucky St | D66: Brackenridge | E66: Active | F66: excluded | G66: Docs outstanding: Court order (O/C) approving postponements covering 3 sale date(s): 7/6/26, 8/3/26, 11/2/26 | H66: 6000 | I66: Free & clear court order, min bid $6,000.00
A67: 93DEC25 | B67: GD-21-011790 | C67: 1310 Ravine St | D67: Munhall | E67: Active | F67: excluded | G67: Docs outstanding: Court order (O/C) approving postponements covering 4 sale date(s): 5/4/26, 7/6/26, 9/8/26, 11/2/26 | H67: 9209.08
A68: 95DEC25 | B68: GD-23-014173 | C68: 516 Firethorne Drive | D68: Monroeville | E68: Active | F68: excluded | G68: Docs outstanding: Court order (O/C) approving postponements covering 1 sale date(s): 11/2/26 | H68: 27528.12
A69: 123DEC25 | B69: MG-25-000069 | C69: 3344 Altherton Drive | D69: Bethel Park | E69: Stayed | F69: excluded | G69: Stayed | H69: 8068.59 | I69: Bankruptcy history: 1 filing(s)
A70: 156DEC25 | B70: MG-14-001071 | C70: 2228 Lacrosse Street | D70: Swissvale | E70: Active | F70: excluded | G70: Bankruptcy dismissal / relief-from-stay docs | H70: 44042.44 | I70: Bankruptcy history: 1 filing(s)
A71: 159DEC25 | B71: GD-22-014187 | C71: 374 Calderwood Avenue | D71: Ross | E71: Postponed to 5/3/2027 | F71: excluded | G71: Postponed to 5/3/2027 | H71: 44287.28
A72: 160DEC25 | B72: GD-24-010503 | C72: 234 Gass Rd | D72: Ross | E72: Active | F72: excluded | G72: Docs outstanding: Court order (O/C) approving postponements covering 3 sale date(s): 7/6/26, 10/5/26, 11/2/26 | H72: 14501.67
A73: 8JAN26 | B73: GD-22-015866 | C73: 406 Richland Ave | D73: Dravosburg | E73: Active | F73: excluded | G73: Non-residential (Commercial) | H73: 23988.1
A74: 18JAN26 | B74: GD-25-002385 | C74: 3069 Scotia Hollow Road | D74: Jefferson Hills | E74: Active | F74: ok | G74: Sheriff OK box checked | H74: 7000 | I74: Free & clear court order, min bid $7,000.00
A75: 20JAN26 | B75: GD-17-003588 | C75: 500 Park Ave | D75: Elizabeth Twp | E75: Active | F75: excluded | G75: Docs outstanding: Rule 3129.3 notice of postponed sale date (for 11/2/26); Court order (O/C) approving postponements covering 1 sale date(s): 11/2/26 | H75: 33432.69
A76: 33JAN26 | B76: MG-24-000809 | C76: 3014 Boyd St | D76: McKeesport | E76: Active | F76: excluded | G76: Bankruptcy dismissal / relief-from-stay docs | H76: 9883.18 | I76: Bankruptcy history: 1 filing(s)
A77: 56JAN26 | B77: MG-25-000290 | C77: 6 Cheryl Drive | D77: Robinson | E77: Stayed | F77: excluded | G77: Stayed | H77: 10193.12
A78: 62JAN26 | B78: GD-25-003317 | C78: 2086 Smithdale Rd | D78: Elizabeth Twp | E78: Active | F78: almost | G78: Only Rule 3129.3 outstanding | H78: 15431.56
A79: 72JAN26 | B79: MG-23-000294 | C79: 5438 Hillcrest St | D79: Pittsburgh | E79: Active | F79: excluded | G79: Docs outstanding: Court order (O/C) approving postponements covering 2 sale date(s): 10/5/26, 11/2/26 | H79: 4876.58 | I79: Defense attorney has entered an appearance
A80: 90JAN26 | B80: GD-23-014428 | C80: 408 Edison Street | D80: West Mifflin | E80: Active | F80: excluded | G80: Docs outstanding: Proof of service on defendant; Court order (O/C) approving postponements covering 3 sale date(s): 7/6/26, 8/3/26, 11/2/26 | H80: 52333.89
A81: 92JAN26 | B81: GD-19-017606 | C81: 605 High St | D81: Versailles | E81: Postponed to 5/3/2027 | F81: excluded | G81: Postponed to 5/3/2027 | H81: 20298.7
A82: 93JAN26 | B82: GD-24-009198 | C82: 3069 Scotia Hollow Road | D82: Jefferson Hills | E82: Active | F82: excluded | G82: Docs outstanding: Court order (O/C) approving postponements covering 1 sale date(s): 11/2/26 | H82: 43166.54
A83: 104JAN26 | B83: GD-23-007949 | C83: 742 Saint Clair Avenue | D83: Clairton | E83: Stayed | F83: excluded | G83: Stayed | H83: 27552.36 | I83: OK-to-sell note dated 8/3/26, not this sale – verify
A84: 105JAN26 | B84: GD-24-009727 | C84: 5532 Front Street | D84: Penn Hills | E84: Active | F84: excluded | G84: Docs outstanding: Court order (O/C) approving postponements covering 1 sale date(s): 11/2/26 | H84: 24804.28 | I84: Bankruptcy history: 1 filing(s)
A85: 14FEB26 | B85: GD-23-010153 | C85: 3013 Mcmillan Road | D85: Robinson | E85: Active | F85: excluded | G85: Docs outstanding: Court order (O/C) approving postponements covering 1 sale date(s): 11/2/26 | H85: 43865.87
A86: 17FEB26 | B86: GD-23-005893 | C86: 1304 Louise Street | D86: Munhall | E86: Active | F86: excluded | G86: Docs outstanding: Court order (O/C) approving postponements covering 2 sale date(s): 8/3/26, 11/2/26 | H86: 48105.24
A87: 18FEB26 | B87: GD-19-001541 | C87: 419 Carl Street | D87: Mount Oliver | E87: Postponed to 5/3/2027 | F87: excluded | G87: Postponed to 5/3/2027 | H87: 69411.63
A88: 40FEB26 | B88: GD-23-009076 | C88: 1201 Fawcett Ave | D88: White Oak | E88: Active | F88: excluded | G88: Docs outstanding: Rule 3129.3 notice of postponed sale date (for 11/2/26); Court order (O/C) approving postponements covering 3 sale date(s): 8/3/26, 9/8/26, 11/2/26 | H88: 41779.16
A89: 58FEB26 | B89: GD-24-011651 | C89: 1709 Wesley St | D89: McKeesport | E89: Active | F89: excluded | G89: Docs outstanding: Court order (O/C) approving postponements covering 2 sale date(s): 8/3/26, 11/2/26 | H89: 21934.9
A90: 78FEB26 | B90: GD-18-007452 | C90: 360 E James St | D90: Munhall | E90: Active | F90: excluded | G90: Docs outstanding: Court order (O/C) approving postponements covering 6 sale date(s): 5/4/26, 6/1/26, 7/6/26, 9/8/26, 10/5/26, 11/2/26 | H90: 32280.82
A91: 90FEB26 | B91: MG-24-000981 | C91: 2111 Carolina Avenue | D91: West Mifflin | E91: Stayed | F91: excluded | G91: Stayed | H91: 2365.12
A92: 112FEB26 | B92: GD-17-009422 | C92: 1309 Singer Pl | D92: Wilkinsburg | E92: Postponed to 12/7/2026 | F92: excluded | G92: Postponed to 12/7/2026 | H92: 90776.83
A93: 114FEB26 | B93: GD-21-006143 | C93: 1221 Margaret St | D93: Munhall | E93: Active | F93: excluded | G93: Docs outstanding: Court order (O/C) approving postponements covering 2 sale date(s): 10/5/26, 11/2/26 | H93: 82708.94
A94: 30MAR26 | B94: GD-25-007997 | C94: 5404 Black St | D94: Pittsburgh | E94: Active | F94: excluded | G94: Bankruptcy dismissal / relief-from-stay docs | H94: 11258.78 | I94: Bankruptcy history: 1 filing(s)
A95: 51MAR26 | B95: GD-19-016819 | C95: 105 Branch St | D95: Carnegie | E95: Postponed to 5/3/2027 | F95: excluded | G95: Postponed to 5/3/2027 | H95: 41760.3
A96: 67MAR26 | B96: MG-25-000393 | C96: 125 Olancha Avenue | D96: Brentwood | E96: Active | F96: ok | G96: Sheriff OK box checked | H96: 6387.14
A97: 70MAR26 | B97: MG-16-001493 | C97: 5076 Lindermer Avenue | D97: Bethel Park | E97: Active | F97: excluded | G97: Bankruptcy dismissal / relief-from-stay docs | H97: 7247.47 | I97: Bankruptcy history: 1 filing(s)
A98: 90MAR26 | B98: GD-24-012379 | C98: 34 Woodruff Dr ; 905 Woodbourne Ave ; 1700 New Haven Ave | D98: Carnegie | E98: Active | F98: excluded | G98: Bankruptcy dismissal / relief-from-stay docs | H98: 51643.75 | I98: Bankruptcy history: 1 filing(s)
A99: 106MAR26 | B99: GD-24-010373 | C99: 606 E 14th Ave | D99: Munhall | E99: Active | F99: almost | G99: VERIFY – Service/3129.2/3129.3 checked, OK not yet checked, no items listed | H99: 65577.98
A100: 107MAR26 | B100: GD-24-012429 | C100: 836 Suismon St ; 838 Suismon St ; 840 Suismon St ; 1500 Edgehill Ave ; 1216 Louise St | D100: Pittsburgh | E100: Active | F100: excluded | G100: Bankruptcy dismissal / relief-from-stay docs | H100: 93816.25 | I100: Bankruptcy history: 1 filing(s)
...

Sheet _Manual
A1: sale_id | B1: assessed_value | C1: max_bid | D1: my_notes | E1: sold_for | F1: bidder_no

Sheet _Meta
A1: sale_date | B1: 2026-11-02
A2: source | B2: November-Sale-List-Updated-10-22.pdf (printed 10/22/2026 2:51:38PM)
A3: last_run | B3: 2026-10-28 04:31
A4: log | B4: 2026-10-25 22:15 | C4: 105 | D4: November-Sale-List-Updated-10-22.pdf (printed 10/22/2026 2:51:38PM) | E4: 17
A5: log | B5: 2026-10-26 04:31 | C5: 105 | D5: November-Sale-List-Updated-10-22.pdf (printed 10/22/2026 2:51:38PM) | E5: 17
A6: log | B6: 2026-10-28 04:31 | C6: 105 | D6: November-Sale-List-Updated-10-22.pdf (printed 10/22/2026 2:51:38PM) | E6: 17
